{"hartalis|solmora-lux":["bastigor",1,7,"Temperate","Standard"],"helzephyr-lux|solmora-lux":["anubis",1,23,"Temperate","Standard"],"helzephyr|solmora-lux":["celesdir",1,26,"Temperate","Standard"],"hoodle|solmora-lux":["loomen",1,38,"Temperate","Standard"],"hangyu-cryst|solmora-lux":["icelyn",1,52,"Temperate","Standard"],"herbil|solmora-lux":["nitemary-botan",1,54,"Temperate","Standard"],"hangyu|solmora-lux":["prunelia",1,57,"Temperate","Standard"],"hoocrates|solmora-lux":["incineram",1,60,"Temperate","Standard"],"hartalis|souffline":["bastigor",1,7,"Temperate","Standard"],"helzephyr-lux|souffline":["anubis",1,23,"Temperate","Standard"],"helzephyr|souffline":["celesdir",1,26,"Temperate","Standard"],"hoodle|souffline":["loomen",1,38,"Temperate","Standard"],"hangyu-cryst|souffline":["icelyn",1,52,"Temperate","Standard"],"herbil|souffline":["nitemary-botan",1,54,"Temperate","Standard"],"hangyu|souffline":["prunelia",1,57,"Temperate","Standard"],"hoocrates|souffline":["incineram",1,60,"Temperate","Standard"],"hartalis|panthalus":["bastigor",1,7,"Temperate","Standard"],"helzephyr-lux|panthalus":["astegon",1,23,"Temperate","Standard"],"helzephyr|panthalus":["celesdir",1,26,"Temperate","Standard"],"hoodle|panthalus":["loomen",1,38,"Temperate","Standard"],"hangyu-cryst|panthalus":["icelyn",1,52,"Temperate","Standard"],"herbil|panthalus":["nitemary-botan",1,54,"Temperate","Standard"],"hangyu|panthalus":["dynamoff",1,57,"Temperate","Standard"],"hoocrates|panthalus":["vaelet",1,60,"Temperate","Standard"],"hartalis|shaolong":["dandilord",1,7,"Temperate","Standard"],"helzephyr-lux|shaolong":["faleris",1,24,"Temperate","Standard"],"helzephyr|shaolong":["beakon-cryst",1,27,"Temperate","Standard"],"hoodle|shaolong":["fenglope-lux",1,39,"Temperate","Standard"],"hangyu-cryst|shaolong":["blazehowl-noct",1,52,"Temperate","Standard"],"herbil|shaolong":["turtacle-terra",1,55,"Temperate","Standard"],"hangyu|shaolong":["leafan",1,57,"Temperate","Standard"],"hoocrates|shaolong":["wixen-noct",1,60,"Temperate","Standard"],"hartalis|jetragon":["silvance",1,8,"Temperate","Standard"],"helzephyr-lux|jetragon":["dualith",1,24,"Temperate","Standard"],"helzephyr|jetragon":["reptyro-cryst",1,27,"Temperate","Standard"],"hoodle|jetragon":["fenglope-lux",1,39,"Temperate","Standard"],"hangyu-cryst|jetragon":["loupmoon-cryst",1,53,"Temperate","Standard"],"herbil|jetragon":["tropicaw",1,55,"Temperate","Standard"],"hangyu|jetragon":["skutlass",1,58,"Temperate","Standard"],"hoocrates|jetragon":["snock-lux",1,61,"Temperate","Standard"],"hartalis|silvance":["jetragon",1,8,"Temperate","Standard"],"helzephyr-lux|silvance":["dupin",1,24,"Temperate","Standard"],"helzephyr|silvance":["reptyro-cryst",1,27,"Temperate","Standard"],"hoodle|silvance":["fenglope-lux",1,39,"Temperate","Standard"],"hangyu-cryst|silvance":["loupmoon-cryst",1,53,"Temperate","Standard"],"herbil|silvance":["tropicaw",1,55,"Temperate","Standard"],"hangyu|silvance":["vanwyrm-cryst",1,58,"Temperate","Standard"],"hoocrates|silvance":["prixter",1,61,"Temperate","Standard"],"hartalis|hartalis":["silvance",1,8,"Temperate","Standard"],"hartalis|orserk":["blazamut-ryu",1,9,"Temperate","Standard"],"hartalis|neptilius":["orserk",1,10,"Temperate","Standard"],"hartalis|jormuntide-ignis":["bellanoir-libero",1,10,"Temperate","Standard"],"hartalis|paladius":["bellanoir-libero",1,10,"Temperate","Standard"],"hartalis|necromus":["eidrolon-ignis",1,10,"Temperate","Standard"],"hartalis|tetroise-primo":["eidrolon-ignis",1,10,"Temperate","Standard"],"hartalis|knocklem-ignis":["frostallion",1,11,"Temperate","Standard"],"hartalis|lyleen-noct":["frostallion",1,11,"Temperate","Standard"],"hartalis|ophydia":["neptilius",1,11,"Temperate","Standard"],"hartalis|lyleen":["neptilius",1,11,"Temperate","Standard"],"hartalis|knocklem":["jormuntide-ignis",1,11,"Temperate","Standard"],"hartalis|solenne":["paladius",1,12,"Temperate","Standard"],"hartalis|renjishi":["necromus",1,12,"Temperate","Standard"],"hartalis|selyne":["lyleen-noct",1,13,"Temperate","Standard"],"hartalis|whalaska-ignis":["ophydia",1,14,"Temperate","Standard"],"hartalis|moldron-cryst":["ophydia",1,14,"Temperate","Standard"],"hartalis|xenolord":["lyleen",1,14,"Temperate","Standard"],"hartalis|starryon-primo":["knocklem",1,15,"Temperate","Standard"],"hartalis|pierdon-cryst":["celesdir-noct",1,15,"Temperate","Standard"],"hartalis|roujay":["eidrolon",1,16,"Temperate","Standard"],"hartalis|univolt-cryst":["eidrolon",1,17,"Temperate","Standard"],"hartalis|shadowbeak":["eidrolon",1,17,"Temperate","Standard"],"hartalis|silvegis":["eidrolon",1,17,"Temperate","Standard"],"hartalis|jormuntide":["selyne",1,18,"Temperate","Standard"],"hartalis|reptyro-cryst":["selyne",1,18,"Temperate","Standard"],"hartalis|wumpo-botan":["selyne",1,18,"Temperate","Standard"],"hartalis|warsect-terra":["selyne",1,18,"Temperate","Standard"],"hartalis|menasting-terra":["selyne",1,19,"Temperate","Standard"],"hartalis|sibelyx-primo":["whalaska-ignis",1,19,"Temperate","Standard"],"hartalis|whalaska":["xenolord",1,20,"Temperate","Standard"],"hartalis|suzaku-aqua":["blazamut",1,20,"Temperate","Standard"],"hartalis|moldron":["azurmane",1,21,"Temperate","Standard"],"hartalis|mycora":["azurmane",1,21,"Temperate","Standard"],"hartalis|relaxaurus-lux":["starryon-primo",1,21,"Temperate","Standard"],"hartalis|splatterina":["starryon-primo",1,21,"Temperate","Standard"],"hartalis|tetroise":["elgrove-cryst",1,21,"Temperate","Standard"],"hartalis|kitsun-noct":["elgrove-cryst",1,22,"Temperate","Standard"],"hartalis|lapure":["faleris-aqua",1,22,"Temperate","Standard"],"hartalis|petallia-ignis":["faleris-aqua",1,22,"Temperate","Standard"],"hartalis|wumpo":["pierdon-cryst",1,22,"Temperate","Standard"],"hartalis|prixter-lux":["cryolinx-terra",1,22,"Temperate","Standard"],"hartalis|sekhmet":["anubis",1,23,"Temperate","Standard"],"hartalis|loomen":["astegon",1,23,"Temperate","Standard"],"hartalis|helzephyr-lux":["dupin",1,24,"Temperate","Standard"],"hartalis|venusa":["roujay",1,25,"Temperate","Standard"],"hartalis|sootseer":["roujay",1,25,"Temperate","Standard"],"hartalis|xenogard":["univolt-cryst",1,25,"Temperate","Standard"],"hartalis|majex":["shadowbeak",1,25,"Temperate","Standard"],"hartalis|ragnahawk":["celesdir",1,26,"Temperate","Standard"],"hartalis|reptyro":["celesdir",1,26,"Temperate","Standard"],"hartalis|mammorest-cryst":["beakon-cryst",1,27,"Temperate","Standard"],"hartalis|relaxaurus":["jormuntide",1,27,"Temperate","Standard"],"hartalis|polapup-terra":["jormuntide",1,27,"Temperate","Standard"],"hartalis|pierdon":["reptyro-cryst",1,27,"Temperate","Standard"],"hartalis|menasting":["reptyro-cryst",1,27,"Temperate","Standard"],"hartalis|helzephyr":["wumpo-botan",1,28,"Temperate","Standard"],"hartalis|omascul":["wumpo-botan",1,28,"Temperate","Standard"],"hartalis|starryon":["bellanoir",1,28,"Temperate","Standard"],"hartalis|verdash":["bellanoir",1,28,"Temperate","Standard"],"hartalis|wistella":["warsect-terra",1,29,"Temperate","Standard"],"hartalis|suzaku":["menasting-terra",1,29,"Temperate","Standard"],"hartalis|quivern":["sibelyx-primo",1,29,"Temperate","Standard"],"hartalis|nitemary":["sibelyx-primo",1,29,"Temperate","Standard"],"hartalis|palumba":["sibelyx-primo",1,30,"Temperate","Standard"],"hartalis|nyafia":["sibelyx-primo",1,30,"Temperate","Standard"],"hartalis|icelyn":["sibelyx-primo",1,30,"Temperate","Standard"],"hartalis|warsect":["whalaska",1,30,"Temperate","Standard"],"hartalis|loupmoon-cryst":["whalaska",1,31,"Temperate","Standard"],"hartalis|quivern-botan":["whalaska",1,31,"Temperate","Standard"],"hartalis|incineram-noct":["whalaska",1,31,"Temperate","Standard"],"hartalis|nitemary-botan":["whalaska",1,31,"Temperate","Standard"],"hartalis|turtacle-terra":["whalaska",1,31,"Temperate","Standard"],"hartalis|mammorest":["whalaska",1,32,"Temperate","Standard"],"hartalis|tropicaw":["ghangler-ignis",1,32,"Temperate","Standard"],"hartalis|solmora":["gildane",1,32,"Temperate","Standard"],"hartalis|prunelia":["suzaku-aqua",1,32,"Temperate","Standard"],"hartalis|leafan":["moldron",1,33,"Temperate","Standard"],"hartalis|skutlass":["moldron",1,33,"Temperate","Standard"],"hartalis|vanwyrm-cryst":["mycora",1,33,"Temperate","Standard"],"hartalis|mossanda-lux":["mycora",1,33,"Temperate","Standard"],"hartalis|shroomer-noct":["relaxaurus-lux",1,34,"Temperate","Standard"],"hartalis|incineram":["splatterina",1,34,"Temperate","Standard"],"hartalis|vaelet":["splatterina",1,34,"Temperate","Standard"],"hartalis|wixen-noct":["tetroise",1,34,"Temperate","Standard"],"hartalis|snock-lux":["tetroise",1,34,"Temperate","Standard"],"hartalis|prixter":["kitsun-noct",1,35,"Temperate","Standard"],"hartalis|shroomer":["kitsun-noct",1,35,"Temperate","Standard"],"hartalis|kingpaca-cryst":["lapure",1,35,"Temperate","Standard"],"hartalis|needoll-noct":["wumpo",1,36,"Temperate","Standard"],"hartalis|skutlass-ignis":["bushi-noct",1,36,"Temperate","Standard"],"hartalis|rayhound-cryst":["bushi-noct",1,36,"Temperate","Standard"],"hartalis|smokie-cryst":["prixter-lux",1,37,"Temperate","Standard"],"hartalis|vanwyrm":["sekhmet",1,37,"Temperate","Standard"],"hartalis|polapup":["sekhmet",1,37,"Temperate","Standard"],"hartalis|kitsun":["ghangler",1,38,"Temperate","Standard"],"hartalis|lapiron":["ghangler",1,38,"Temperate","Standard"],"hartalis|maraith":["fenglope-lux",1,38,"Temperate","Standard"],"hartalis|petallia":["fenglope-lux",1,39,"Temperate","Standard"],"hartalis|tarantriss":["fenglope-lux",1,39,"Temperate","Standard"],"hartalis|mimog":["fenglope-lux",1,39,"Temperate","Standard"],"hartalis|slowatt":["fenglope-lux",1,39,"Temperate","Standard"],"hartalis|smokie":["fenglope-lux",1,39,"Temperate","Standard"],"hartalis|hoodle":["fenglope-lux",1,40,"Temperate","Standard"],"hartalis|snock":["helzephyr-lux",1,40,"Temperate","Standard"],"hartalis|katress-ignis":["helzephyr-lux",1,40,"Temperate","Standard"],"hartalis|sibelyx":["helzephyr-lux",1,40,"Temperate","Standard"],"hartalis|xenovader":["helzephyr-lux",1,40,"Temperate","Standard"],"hartalis|surfent-terra":["helzephyr-lux",1,41,"Temperate","Standard"],"hartalis|penking-lux":["venusa",1,41,"Temperate","Standard"],"hartalis|pyrin-noct":["sootseer",1,41,"Temperate","Standard"],"hartalis|valentail":["xenogard",1,42,"Temperate","Standard"],"hartalis|rayhound":["majex",1,42,"Temperate","Standard"],"hartalis|reindrix":["majex",1,42,"Temperate","Standard"],"hartalis|pyrin":["braloha",1,43,"Temperate","Standard"],"hartalis|lullu":["cryolinx",1,44,"Temperate","Standard"],"hartalis|lunaris":["ragnahawk",1,44,"Temperate","Standard"],"hartalis|woolipop-terra":["reptyro",1,44,"Temperate","Standard"],"hartalis|katress":["reptyro",1,45,"Temperate","Standard"],"hartalis|robinquill-terra":["mammorest-cryst",1,45,"Temperate","Standard"],"hartalis|mossanda":["mammorest-cryst",1,45,"Temperate","Standard"],"hartalis|penking":["broncherry-aqua",1,45,"Temperate","Standard"],"hartalis|wixen":["broncherry-aqua",1,45,"Temperate","Standard"],"hartalis|lovander":["relaxaurus",1,45,"Temperate","Standard"],"hartalis|loupmoon":["polapup-terra",1,46,"Temperate","Standard"],"hartalis|munchill":["pierdon",1,46,"Temperate","Standard"],"hartalis|sweepa":["menasting",1,47,"Temperate","Standard"],"hartalis|kingpaca":["starryon",1,48,"Temperate","Standard"],"hartalis|yakumo":["verdash",1,48,"Temperate","Standard"],"hartalis|wispaw":["gildra",1,48,"Temperate","Standard"],"hartalis|robinquill":["gildra",1,49,"Temperate","Standard"],"hartalis|univolt":["wistella",1,49,"Temperate","Standard"],"hartalis|kikit":["suzaku",1,50,"Temperate","Standard"],"hartalis|tombat":["quivern",1,50,"Temperate","Standard"],"hartalis|puffolt":["azurobe-cryst",1,50,"Temperate","Standard"],"hartalis|snugloo":["palumba",1,51,"Temperate","Standard"],"hartalis|turtacle":["nyafia",1,51,"Temperate","Standard"],"hartalis|needoll":["nyafia",1,52,"Temperate","Standard"],"hartalis|surfent":["icelyn",1,52,"Temperate","Standard"],"hartalis|ribbuny-botan":["blazehowl-noct",1,52,"Temperate","Standard"],"hartalis|kelpsea-ignis":["warsect",1,52,"Temperate","Standard"],"hartalis|muffly":["warsect",1,53,"Temperate","Standard"],"hartalis|pengullet-lux":["loupmoon-cryst",1,53,"Temperate","Standard"],"hangyu-cryst|hartalis":["quivern-botan",1,53,"Temperate","Standard"],"hartalis|killamari-primo":["incineram-noct",1,54,"Temperate","Standard"],"hartalis|nitewing":["nitemary-botan",1,54,"Temperate","Standard"],"hartalis|jellroy":["mammorest",1,55,"Temperate","Standard"],"hartalis|herbil":["blazehowl",1,55,"Temperate","Standard"],"hartalis|leezpunk-ignis":["blazehowl",1,56,"Temperate","Standard"],"hartalis|jelliette":["solmora",1,56,"Temperate","Standard"],"hartalis|leezpunk":["broncherry",1,56,"Temperate","Standard"],"hartalis|melpaca":["dynamoff",1,57,"Temperate","Standard"],"hartalis|tocotoco":["leafan",1,57,"Temperate","Standard"],"hartalis|mau-cryst":["skutlass",1,58,"Temperate","Standard"],"hartalis|killamari":["vanwyrm-cryst",1,58,"Temperate","Standard"],"hangyu|hartalis":["vanwyrm-cryst",1,58,"Temperate","Standard"],"hartalis|mozzarina":["mossanda-lux",1,59,"Temperate","Standard"],"hartalis|kelpsea":["shroomer-noct",1,59,"Temperate","Standard"],"hartalis|woolipop":["shroomer-noct",1,59,"Temperate","Standard"],"hartalis|tanzee-ignis":["dogen",1,59,"Temperate","Standard"],"hartalis|swee":["dogen",1,59,"Temperate","Standard"],"hartalis|jolthog-cryst":["incineram",1,60,"Temperate","Standard"],"hartalis|ribbuny":["incineram",1,60,"Temperate","Standard"],"hartalis|rooby":["vaelet",1,60,"Temperate","Standard"],"hartalis|rushoar":["vaelet",1,60,"Temperate","Standard"],"hartalis|tanzee":["wixen-noct",1,60,"Temperate","Standard"],"hartalis|nox":["snock-lux",1,61,"Temperate","Standard"],"hartalis|pupperai":["prixter",1,61,"Temperate","Standard"],"hartalis|hoocrates":["prixter",1,61,"Temperate","Standard"],"hartalis|pengullet":["shroomer",1,62,"Temperate","Standard"],"hartalis|sparkit":["digtoise",1,62,"Temperate","Standard"],"hartalis|lifmunk":["digtoise",1,63,"Temperate","Standard"],"hartalis|jolthog":["bushi",1,63,"Temperate","Standard"],"hartalis|mau":["bushi",1,63,"Temperate","Standard"],"hartalis|lamball":["felbat",1,63,"Temperate","Standard"],"hartalis|vixy":["felbat",1,63,"Temperate","Standard"],"hartalis|teafant":["needoll-noct",1,64,"Temperate","Standard"],"hartalis|illuminant-bat":["skutlass-ignis",1,64,"Temperate","Standard"],"hartalis|illuminant-slime":["skutlass-ignis",1,64,"Temperate","Standard"],"hartalis|purple-slime":["skutlass-ignis",1,64,"Temperate","Standard"],"hartalis|rainbow-slime":["skutlass-ignis",1,64,"Temperate","Standard"],"hartalis|red-slime":["skutlass-ignis",1,64,"Temperate","Standard"],"helzephyr-lux|orserk":["univolt-cryst",1,25,"Temperate","Standard"],"helzephyr|orserk":["bellanoir",1,28,"Temperate","Standard"],"hoodle|orserk":["helzephyr-lux",1,40,"Temperate","Standard"],"hangyu-cryst|orserk":["incineram-noct",1,54,"Temperate","Standard"],"herbil|orserk":["solmora",1,56,"Temperate","Standard"],"hangyu|orserk":["shroomer-noct",1,59,"Temperate","Standard"],"hoocrates|orserk":["kingpaca-cryst",1,62,"Temperate","Standard"],"helzephyr-lux|neptilius":["silvegis",1,26,"Temperate","Standard"],"helzephyr|neptilius":["menasting-terra",1,29,"Temperate","Standard"],"hoodle|neptilius":["helzephyr-lux",1,41,"Temperate","Standard"],"hangyu-cryst|neptilius":["turtacle-terra",1,55,"Temperate","Standard"],"herbil|neptilius":["prunelia",1,57,"Temperate","Standard"],"hangyu|neptilius":["incineram",1,60,"Temperate","Standard"],"hoocrates|neptilius":["digtoise",1,62,"Temperate","Standard"],"helzephyr-lux|jormuntide-ignis":["silvegis",1,26,"Temperate","Standard"],"helzephyr|jormuntide-ignis":["sibelyx-primo",1,29,"Temperate","Standard"],"hoodle|jormuntide-ignis":["venusa",1,41,"Temperate","Standard"],"hangyu-cryst|jormuntide-ignis":["mammorest",1,55,"Temperate","Standard"],"herbil|jormuntide-ignis":["dynamoff",1,57,"Temperate","Standard"],"hangyu|jormuntide-ignis":["incineram",1,60,"Temperate","Standard"],"hoocrates|jormuntide-ignis":["digtoise",1,63,"Temperate","Standard"],"helzephyr-lux|paladius":["celesdir",1,26,"Temperate","Standard"],"helzephyr|paladius":["sibelyx-primo",1,29,"Temperate","Standard"],"hoodle|paladius":["venusa",1,41,"Temperate","Standard"],"hangyu-cryst|paladius":["mammorest",1,55,"Temperate","Standard"],"herbil|paladius":["dynamoff",1,57,"Temperate","Standard"],"hangyu|paladius":["vaelet",1,60,"Temperate","Standard"],"hoocrates|paladius":["bushi",1,63,"Temperate","Standard"],"helzephyr-lux|necromus":["celesdir",1,26,"Temperate","Standard"],"helzephyr|necromus":["sibelyx-primo",1,29,"Temperate","Standard"],"hoodle|necromus":["sootseer",1,41,"Temperate","Standard"],"hangyu-cryst|necromus":["tropicaw",1,55,"Temperate","Standard"],"herbil|necromus":["leafan",1,57,"Temperate","Standard"],"hangyu|necromus":["vaelet",1,60,"Temperate","Standard"],"hoocrates|necromus":["bushi",1,63,"Temperate","Standard"],"helzephyr-lux|tetroise-primo":["beakon-cryst",1,27,"Temperate","Standard"],"helzephyr|tetroise-primo":["sibelyx-primo",1,30,"Temperate","Standard"],"hoodle|tetroise-primo":["sootseer",1,42,"Temperate","Standard"],"hangyu-cryst|tetroise-primo":["tropicaw",1,55,"Temperate","Standard"],"herbil|tetroise-primo":["leafan",1,57,"Temperate","Standard"],"hangyu|tetroise-primo":["wixen-noct",1,60,"Temperate","Standard"],"hoocrates|tetroise-primo":["felbat",1,63,"Temperate","Standard"],"helzephyr-lux|knocklem-ignis":["beakon-cryst",1,27,"Temperate","Standard"],"helzephyr|knocklem-ignis":["sibelyx-primo",1,30,"Temperate","Standard"],"hoodle|knocklem-ignis":["xenogard",1,42,"Temperate","Standard"],"hangyu-cryst|knocklem-ignis":["blazehowl",1,55,"Temperate","Standard"],"herbil|knocklem-ignis":["skutlass",1,58,"Temperate","Standard"],"hangyu|knocklem-ignis":["wixen-noct",1,60,"Temperate","Standard"],"hoocrates|knocklem-ignis":["felbat",1,63,"Temperate","Standard"],"helzephyr-lux|lyleen-noct":["jormuntide",1,27,"Temperate","Standard"],"helzephyr|lyleen-noct":["sibelyx-primo",1,30,"Temperate","Standard"],"hoodle|lyleen-noct":["xenogard",1,42,"Temperate","Standard"],"hangyu-cryst|lyleen-noct":["blazehowl",1,56,"Temperate","Standard"],"herbil|lyleen-noct":["skutlass",1,58,"Temperate","Standard"],"hangyu|lyleen-noct":["snock-lux",1,61,"Temperate","Standard"],"hoocrates|lyleen-noct":["needoll-noct",1,64,"Temperate","Standard"],"helzephyr-lux|ophydia":["jormuntide",1,27,"Temperate","Standard"],"helzephyr|ophydia":["sibelyx-primo",1,30,"Temperate","Standard"],"hoodle|ophydia":["xenogard",1,42,"Temperate","Standard"],"hangyu-cryst|ophydia":["solmora",1,56,"Temperate","Standard"],"herbil|ophydia":["vanwyrm-cryst",1,58,"Temperate","Standard"],"hangyu|ophydia":["snock-lux",1,61,"Temperate","Standard"],"hoocrates|ophydia":["needoll-noct",1,64,"Temperate","Standard"],"helzephyr-lux|lyleen":["reptyro-cryst",1,27,"Temperate","Standard"],"helzephyr|lyleen":["whalaska",1,30,"Temperate","Standard"],"hoodle|lyleen":["majex",1,42,"Temperate","Standard"],"hangyu-cryst|lyleen":["solmora",1,56,"Temperate","Standard"],"herbil|lyleen":["vanwyrm-cryst",1,58,"Temperate","Standard"],"hangyu|lyleen":["prixter",1,61,"Temperate","Standard"],"hoocrates|lyleen":["skutlass-ignis",1,64,"Temperate","Standard"],"helzephyr-lux|knocklem":["wumpo-botan",1,28,"Temperate","Standard"],"helzephyr|knocklem":["whalaska",1,31,"Temperate","Standard"],"hoodle|knocklem":["majex",1,43,"Temperate","Standard"],"hangyu-cryst|knocklem":["broncherry",1,56,"Temperate","Standard"],"herbil|knocklem":["mossanda-lux",1,59,"Temperate","Standard"],"hangyu|knocklem":["shroomer",1,61,"Temperate","Standard"],"hoocrates|knocklem":["rayhound-cryst",1,64,"Temperate","Standard"],"helzephyr-lux|solenne":["bellanoir",1,28,"Temperate","Standard"],"helzephyr|solenne":["whalaska",1,31,"Temperate","Standard"],"hoodle|solenne":["grizzbolt",1,43,"Temperate","Standard"],"hangyu-cryst|solenne":["prunelia",1,57,"Temperate","Standard"],"herbil|solenne":["shroomer-noct",1,59,"Temperate","Standard"],"hangyu|solenne":["kingpaca-cryst",1,62,"Temperate","Standard"],"hoocrates|solenne":["smokie-cryst",1,65,"Temperate","Standard"],"helzephyr-lux|renjishi":["bellanoir",1,28,"Temperate","Standard"],"helzephyr|renjishi":["whalaska",1,31,"Temperate","Standard"],"hoodle|renjishi":["braloha",1,43,"Temperate","Standard"],"hangyu-cryst|renjishi":["dynamoff",1,57,"Temperate","Standard"],"herbil|renjishi":["dogen",1,59,"Temperate","Standard"],"hangyu|renjishi":["kingpaca-cryst",1,62,"Temperate","Standard"],"hoocrates|renjishi":["smokie-cryst",1,65,"Temperate","Standard"],"helzephyr-lux|selyne":["sibelyx-primo",1,29,"Temperate","Standard"],"helzephyr|selyne":["suzaku-aqua",1,33,"Temperate","Standard"],"hoodle|selyne":["reptyro",1,45,"Temperate","Standard"],"hangyu-cryst|selyne":["vanwyrm-cryst",1,58,"Temperate","Standard"],"herbil|selyne":["wixen-noct",1,60,"Temperate","Standard"],"hangyu|selyne":["felbat",1,63,"Temperate","Standard"],"hoocrates|selyne":["vanwyrm",1,66,"Temperate","Standard"],"helzephyr-lux|whalaska-ignis":["sibelyx-primo",1,30,"Temperate","Standard"],"helzephyr|whalaska-ignis":["moldron",1,33,"Temperate","Standard"],"hoodle|whalaska-ignis":["mammorest-cryst",1,45,"Temperate","Standard"],"hangyu-cryst|whalaska-ignis":["mossanda-lux",1,58,"Temperate","Standard"],"herbil|whalaska-ignis":["snock-lux",1,61,"Temperate","Standard"],"hangyu|whalaska-ignis":["felbat",1,63,"Temperate","Standard"],"hoocrates|whalaska-ignis":["vanwyrm",1,66,"Temperate","Standard"],"helzephyr-lux|moldron-cryst":["sibelyx-primo",1,30,"Temperate","Standard"],"helzephyr|moldron-cryst":["moldron",1,33,"Temperate","Standard"],"hoodle|moldron-cryst":["mammorest-cryst",1,45,"Temperate","Standard"],"hangyu-cryst|moldron-cryst":["mossanda-lux",1,59,"Temperate","Standard"],"herbil|moldron-cryst":["snock-lux",1,61,"Temperate","Standard"],"hangyu|moldron-cryst":["needoll-noct",1,64,"Temperate","Standard"],"hoocrates|moldron-cryst":["polapup",1,67,"Temperate","Standard"],"helzephyr-lux|xenolord":["sibelyx-primo",1,30,"Temperate","Standard"],"helzephyr|xenolord":["mycora",1,33,"Temperate","Standard"],"hoodle|xenolord":["broncherry-aqua",1,45,"Temperate","Standard"],"hangyu-cryst|xenolord":["shroomer-noct",1,59,"Temperate","Standard"],"herbil|xenolord":["prixter",1,61,"Temperate","Standard"],"hangyu|xenolord":["skutlass-ignis",1,64,"Temperate","Standard"],"hoocrates|xenolord":["kitsun",1,67,"Temperate","Standard"],"helzephyr-lux|starryon-primo":["whalaska",1,31,"Temperate","Standard"],"helzephyr|starryon-primo":["splatterina",1,34,"Temperate","Standard"],"hoodle|starryon-primo":["polapup-terra",1,46,"Temperate","Standard"],"hangyu-cryst|starryon-primo":["incineram",1,60,"Temperate","Standard"],"herbil|starryon-primo":["kingpaca-cryst",1,62,"Temperate","Standard"],"hangyu|starryon-primo":["rayhound-cryst",1,65,"Temperate","Standard"],"hoocrates|starryon-primo":["lapiron",1,68,"Temperate","Standard"],"helzephyr-lux|pierdon-cryst":["whalaska",1,31,"Temperate","Standard"],"helzephyr|pierdon-cryst":["tetroise",1,34,"Temperate","Standard"],"hoodle|pierdon-cryst":["pierdon",1,46,"Temperate","Standard"],"hangyu-cryst|pierdon-cryst":["vaelet",1,60,"Temperate","Standard"],"herbil|pierdon-cryst":["bakemi",1,62,"Temperate","Standard"],"hangyu|pierdon-cryst":["dumud-gild",1,65,"Temperate","Standard"],"hoocrates|pierdon-cryst":["carnibora",1,68,"Temperate","Standard"],"helzephyr-lux|roujay":["suzaku-aqua",1,33,"Temperate","Standard"],"helzephyr|roujay":["wumpo",1,36,"Temperate","Standard"],"hoodle|roujay":["starryon",1,48,"Temperate","Standard"],"hangyu-cryst|roujay":["shroomer",1,61,"Temperate","Standard"],"herbil|roujay":["needoll-noct",1,64,"Temperate","Standard"],"hangyu|roujay":["vanwyrm",1,66,"Temperate","Standard"],"hoocrates|roujay":["tarantriss",1,69,"Temperate","Standard"],"helzephyr-lux|univolt-cryst":["moldron",1,33,"Temperate","Standard"],"helzephyr|univolt-cryst":["wumpo",1,36,"Temperate","Standard"],"hoodle|univolt-cryst":["starryon",1,48,"Temperate","Standard"],"hangyu-cryst|univolt-cryst":["shroomer",1,62,"Temperate","Standard"],"herbil|univolt-cryst":["needoll-noct",1,64,"Temperate","Standard"],"hangyu|univolt-cryst":["polapup",1,67,"Temperate","Standard"],"hoocrates|univolt-cryst":["mimog",1,70,"Temperate","Standard"],"helzephyr-lux|shadowbeak":["moldron",1,33,"Temperate","Standard"],"helzephyr|shadowbeak":["bushi-noct",1,36,"Temperate","Standard"],"hoodle|shadowbeak":["verdash",1,48,"Temperate","Standard"],"hangyu-cryst|shadowbeak":["kingpaca-cryst",1,62,"Temperate","Standard"],"herbil|shadowbeak":["skutlass-ignis",1,64,"Temperate","Standard"],"hangyu|shadowbeak":["polapup",1,67,"Temperate","Standard"],"hoocrates|shadowbeak":["mimog",1,70,"Temperate","Standard"],"helzephyr-lux|silvegis":["mycora",1,33,"Temperate","Standard"],"helzephyr|silvegis":["bushi-noct",1,36,"Temperate","Standard"],"hoodle|silvegis":["verdash",1,48,"Temperate","Standard"],"hangyu-cryst|silvegis":["kingpaca-cryst",1,62,"Temperate","Standard"],"herbil|silvegis":["skutlass-ignis",1,64,"Temperate","Standard"],"hangyu|silvegis":["kitsun",1,67,"Temperate","Standard"],"hoocrates|silvegis":["slowatt",1,70,"Temperate","Standard"],"helzephyr-lux|jormuntide":["relaxaurus-lux",1,34,"Temperate","Standard"],"helzephyr|jormuntide":["frostplume",1,37,"Temperate","Standard"],"hoodle|jormuntide":["wistella",1,49,"Temperate","Standard"],"hangyu-cryst|jormuntide":["digtoise",1,62,"Temperate","Standard"],"herbil|jormuntide":["smokie-cryst",1,65,"Temperate","Standard"],"hangyu|jormuntide":["lapiron",1,68,"Temperate","Standard"],"hoocrates|jormuntide":["smokie",1,70,"Temperate","Standard"],"helzephyr-lux|reptyro-cryst":["splatterina",1,34,"Temperate","Standard"],"helzephyr|reptyro-cryst":["frostplume",1,37,"Temperate","Standard"],"hoodle|reptyro-cryst":["wistella",1,49,"Temperate","Standard"],"hangyu-cryst|reptyro-cryst":["digtoise",1,63,"Temperate","Standard"],"herbil|reptyro-cryst":["smokie-cryst",1,65,"Temperate","Standard"],"hangyu|reptyro-cryst":["beakon",1,68,"Temperate","Standard"],"hoocrates|reptyro-cryst":["hoodle",1,71,"Temperate","Standard"],"helzephyr-lux|wumpo-botan":["splatterina",1,34,"Temperate","Standard"],"helzephyr|wumpo-botan":["sekhmet",1,37,"Temperate","Standard"],"hoodle|wumpo-botan":["bulldosu",1,49,"Temperate","Standard"],"hangyu-cryst|wumpo-botan":["bushi",1,63,"Temperate","Standard"],"herbil|wumpo-botan":["dumud-gild",1,65,"Temperate","Standard"],"hangyu|wumpo-botan":["beakon",1,68,"Temperate","Standard"],"hoocrates|wumpo-botan":["hoodle",1,71,"Temperate","Standard"],"helzephyr-lux|warsect-terra":["tetroise",1,34,"Temperate","Standard"],"helzephyr|warsect-terra":["ghangler",1,38,"Temperate","Standard"],"hoodle|warsect-terra":["suzaku",1,50,"Temperate","Standard"],"hangyu-cryst|warsect-terra":["felbat",1,63,"Temperate","Standard"],"herbil|warsect-terra":["gloopie-primo",1,65,"Temperate","Standard"],"hangyu|warsect-terra":["carnibora",1,68,"Temperate","Standard"],"hoocrates|warsect-terra":["snock",1,71,"Temperate","Standard"],"helzephyr-lux|menasting-terra":["kitsun-noct",1,35,"Temperate","Standard"],"helzephyr|menasting-terra":["ghangler",1,38,"Temperate","Standard"],"hoodle|menasting-terra":["suzaku",1,50,"Temperate","Standard"],"hangyu-cryst|menasting-terra":["felbat",1,63,"Temperate","Standard"],"herbil|menasting-terra":["gloopie-primo",1,66,"Temperate","Standard"],"hangyu|menasting-terra":["maraith",1,68,"Temperate","Standard"],"hoocrates|menasting-terra":["elizabee",1,71,"Temperate","Standard"],"helzephyr-lux|sibelyx-primo":["kitsun-noct",1,35,"Temperate","Standard"],"helzephyr|sibelyx-primo":["loomen",1,38,"Temperate","Standard"],"hoodle|sibelyx-primo":["quivern",1,50,"Temperate","Standard"],"hangyu-cryst|sibelyx-primo":["needoll-noct",1,64,"Temperate","Standard"],"herbil|sibelyx-primo":["elphidran-aqua",1,66,"Temperate","Standard"],"hangyu|sibelyx-primo":["maraith",1,69,"Temperate","Standard"],"hoocrates|sibelyx-primo":["elizabee",1,72,"Temperate","Standard"],"helzephyr-lux|whalaska":["wumpo",1,36,"Temperate","Standard"],"helzephyr|whalaska":["fenglope-lux",1,39,"Temperate","Standard"],"hoodle|whalaska":["palumba",1,51,"Temperate","Standard"],"hangyu-cryst|whalaska":["smokie-cryst",1,65,"Temperate","Standard"],"herbil|whalaska":["kitsun",1,67,"Temperate","Standard"],"hangyu|whalaska":["mimog",1,70,"Temperate","Standard"],"hoocrates|whalaska":["xenovader",1,73,"Temperate","Standard"],"helzephyr-lux|suzaku-aqua":["prixter-lux",1,37,"Temperate","Standard"],"helzephyr|suzaku-aqua":["helzephyr-lux",1,40,"Temperate","Standard"],"hoodle|suzaku-aqua":["nyafia",1,52,"Temperate","Standard"],"hangyu-cryst|suzaku-aqua":["dumud-gild",1,65,"Temperate","Standard"],"herbil|suzaku-aqua":["lapiron",1,68,"Temperate","Standard"],"hangyu|suzaku-aqua":["smokie",1,70,"Temperate","Standard"],"hoocrates|suzaku-aqua":["surfent-terra",1,73,"Temperate","Standard"],"helzephyr-lux|moldron":["prixter-lux",1,37,"Temperate","Standard"],"helzephyr|moldron":["helzephyr-lux",1,40,"Temperate","Standard"],"hoodle|moldron":["icelyn",1,52,"Temperate","Standard"],"hangyu-cryst|moldron":["gloopie-primo",1,65,"Temperate","Standard"],"herbil|moldron":["beakon",1,68,"Temperate","Standard"],"hangyu|moldron":["smokie",1,70,"Temperate","Standard"],"hoocrates|moldron":["surfent-terra",1,73,"Temperate","Standard"],"helzephyr-lux|mycora":["frostplume",1,37,"Temperate","Standard"],"helzephyr|mycora":["helzephyr-lux",1,40,"Temperate","Standard"],"hoodle|mycora":["icelyn",1,52,"Temperate","Standard"],"hangyu-cryst|mycora":["gloopie-primo",1,66,"Temperate","Standard"],"herbil|mycora":["beakon",1,68,"Temperate","Standard"],"hangyu|mycora":["hoodle",1,71,"Temperate","Standard"],"hoocrates|mycora":["penking-lux",1,74,"Temperate","Standard"],"helzephyr-lux|relaxaurus-lux":["frostplume",1,37,"Temperate","Standard"],"helzephyr|relaxaurus-lux":["helzephyr-lux",1,40,"Temperate","Standard"],"hoodle|relaxaurus-lux":["blazehowl-noct",1,52,"Temperate","Standard"],"hangyu-cryst|relaxaurus-lux":["elphidran-aqua",1,66,"Temperate","Standard"],"herbil|relaxaurus-lux":["carnibora",1,68,"Temperate","Standard"],"hangyu|relaxaurus-lux":["hoodle",1,71,"Temperate","Standard"],"hoocrates|relaxaurus-lux":["penking-lux",1,74,"Temperate","Standard"],"helzephyr-lux|splatterina":["sekhmet",1,37,"Temperate","Standard"],"helzephyr|splatterina":["helzephyr-lux",1,40,"Temperate","Standard"],"hoodle|splatterina":["blazehowl-noct",1,52,"Temperate","Standard"],"hangyu-cryst|splatterina":["elphidran-aqua",1,66,"Temperate","Standard"],"herbil|splatterina":["carnibora",1,68,"Temperate","Standard"],"hangyu|splatterina":["snock",1,71,"Temperate","Standard"],"hoocrates|splatterina":["croajiro-noct",1,74,"Temperate","Standard"],"helzephyr-lux|tetroise":["sekhmet",1,37,"Temperate","Standard"],"helzephyr|tetroise":["helzephyr-lux",1,41,"Temperate","Standard"],"hoodle|tetroise":["warsect",1,52,"Temperate","Standard"],"hangyu-cryst|tetroise":["vanwyrm",1,66,"Temperate","Standard"],"herbil|tetroise":["maraith",1,68,"Temperate","Standard"],"hangyu|tetroise":["snock",1,71,"Temperate","Standard"],"hoocrates|tetroise":["croajiro-noct",1,74,"Temperate","Standard"],"helzephyr-lux|kitsun-noct":["ghangler",1,38,"Temperate","Standard"],"helzephyr|kitsun-noct":["helzephyr-lux",1,41,"Temperate","Standard"],"hoodle|kitsun-noct":["warsect",1,53,"Temperate","Standard"],"hangyu-cryst|kitsun-noct":["vanwyrm",1,66,"Temperate","Standard"],"herbil|kitsun-noct":["maraith",1,69,"Temperate","Standard"],"hangyu|kitsun-noct":["elizabee",1,71,"Temperate","Standard"],"hoocrates|kitsun-noct":["pyrin-noct",1,74,"Temperate","Standard"],"helzephyr-lux|lapure":["ghangler",1,38,"Temperate","Standard"],"helzephyr|lapure":["venusa",1,41,"Temperate","Standard"],"hoodle|lapure":["loupmoon-cryst",1,53,"Temperate","Standard"],"hangyu-cryst|lapure":["polapup",1,67,"Temperate","Standard"],"herbil|lapure":["petallia",1,69,"Temperate","Standard"],"hangyu|lapure":["elizabee",1,72,"Temperate","Standard"],"hoocrates|lapure":["pyrin-noct",1,75,"Temperate","Standard"],"helzephyr-lux|petallia-ignis":["loomen",1,38,"Temperate","Standard"],"helzephyr|petallia-ignis":["venusa",1,41,"Temperate","Standard"],"hoodle|petallia-ignis":["loupmoon-cryst",1,53,"Temperate","Standard"],"hangyu-cryst|petallia-ignis":["polapup",1,67,"Temperate","Standard"],"herbil|petallia-ignis":["petallia",1,69,"Temperate","Standard"],"hangyu|petallia-ignis":["katress-ignis",1,72,"Temperate","Standard"],"hoocrates|petallia-ignis":["gorirat-terra",1,75,"Temperate","Standard"],"helzephyr-lux|wumpo":["loomen",1,38,"Temperate","Standard"],"helzephyr|wumpo":["sootseer",1,41,"Temperate","Standard"],"hoodle|wumpo":["quivern-botan",1,53,"Temperate","Standard"],"hangyu-cryst|wumpo":["kitsun",1,67,"Temperate","Standard"],"herbil|wumpo":["tarantriss",1,69,"Temperate","Standard"],"hangyu|wumpo":["katress-ignis",1,72,"Temperate","Standard"],"hoocrates|wumpo":["gorirat-terra",1,75,"Temperate","Standard"],"helzephyr-lux|prixter-lux":["fenglope-lux",1,39,"Temperate","Standard"],"helzephyr|prixter-lux":["xenogard",1,42,"Temperate","Standard"],"hoodle|prixter-lux":["incineram-noct",1,54,"Temperate","Standard"],"hangyu-cryst|prixter-lux":["lapiron",1,67,"Temperate","Standard"],"herbil|prixter-lux":["mimog",1,70,"Temperate","Standard"],"hangyu|prixter-lux":["sibelyx",1,72,"Temperate","Standard"],"hoocrates|prixter-lux":["dinossom-lux",1,75,"Temperate","Standard"],"helzephyr-lux|sekhmet":["fenglope-lux",1,39,"Temperate","Standard"],"helzephyr|sekhmet":["xenogard",1,42,"Temperate","Standard"],"hoodle|sekhmet":["nitemary-botan",1,54,"Temperate","Standard"],"hangyu-cryst|sekhmet":["beakon",1,68,"Temperate","Standard"],"herbil|sekhmet":["slowatt",1,70,"Temperate","Standard"],"hangyu|sekhmet":["xenovader",1,73,"Temperate","Standard"],"hoocrates|sekhmet":["valentail",1,76,"Temperate","Standard"],"helzephyr-lux|loomen":["fenglope-lux",1,39,"Temperate","Standard"],"helzephyr|loomen":["majex",1,42,"Temperate","Standard"],"hoodle|loomen":["turtacle-terra",1,54,"Temperate","Standard"],"hangyu-cryst|loomen":["carnibora",1,68,"Temperate","Standard"],"herbil|loomen":["smokie",1,70,"Temperate","Standard"],"hangyu|loomen":["azurobe",1,73,"Temperate","Standard"],"hoocrates|loomen":["dazzi-noct",1,76,"Temperate","Standard"],"helzephyr-lux|helzephyr-lux":["venusa",1,41,"Temperate","Standard"],"helzephyr-lux|venusa":["sootseer",1,41,"Temperate","Standard"],"helzephyr-lux|sootseer":["venusa",1,41,"Temperate","Standard"],"helzephyr-lux|xenogard":["venusa",1,41,"Temperate","Standard"],"helzephyr-lux|majex":["sootseer",1,42,"Temperate","Standard"],"helzephyr-lux|ragnahawk":["majex",1,42,"Temperate","Standard"],"helzephyr-lux|reptyro":["majex",1,42,"Temperate","Standard"],"helzephyr-lux|mammorest-cryst":["majex",1,43,"Temperate","Standard"],"helzephyr-lux|relaxaurus":["grizzbolt",1,43,"Temperate","Standard"],"helzephyr-lux|polapup-terra":["braloha",1,43,"Temperate","Standard"],"helzephyr-lux|pierdon":["braloha",1,43,"Temperate","Standard"],"helzephyr-lux|menasting":["cryolinx",1,44,"Temperate","Standard"],"helzephyr|helzephyr-lux":["cryolinx",1,44,"Temperate","Standard"],"helzephyr-lux|omascul":["ragnahawk",1,44,"Temperate","Standard"],"helzephyr-lux|starryon":["ragnahawk",1,44,"Temperate","Standard"],"helzephyr-lux|verdash":["reptyro",1,44,"Temperate","Standard"],"helzephyr-lux|wistella":["mammorest-cryst",1,45,"Temperate","Standard"],"helzephyr-lux|suzaku":["broncherry-aqua",1,45,"Temperate","Standard"],"helzephyr-lux|quivern":["broncherry-aqua",1,45,"Temperate","Standard"],"helzephyr-lux|nitemary":["relaxaurus",1,46,"Temperate","Standard"],"helzephyr-lux|palumba":["polapup-terra",1,46,"Temperate","Standard"],"helzephyr-lux|nyafia":["polapup-terra",1,46,"Temperate","Standard"],"helzephyr-lux|icelyn":["pierdon",1,46,"Temperate","Standard"],"helzephyr-lux|warsect":["menasting",1,47,"Temperate","Standard"],"helzephyr-lux|loupmoon-cryst":["menasting",1,47,"Temperate","Standard"],"helzephyr-lux|quivern-botan":["helzephyr",1,47,"Temperate","Standard"],"helzephyr-lux|incineram-noct":["helzephyr",1,47,"Temperate","Standard"],"helzephyr-lux|nitemary-botan":["omascul",1,47,"Temperate","Standard"],"helzephyr-lux|turtacle-terra":["omascul",1,47,"Temperate","Standard"],"helzephyr-lux|mammorest":["starryon",1,48,"Temperate","Standard"],"helzephyr-lux|tropicaw":["starryon",1,48,"Temperate","Standard"],"helzephyr-lux|solmora":["verdash",1,48,"Temperate","Standard"],"helzephyr-lux|prunelia":["gildra",1,49,"Temperate","Standard"],"helzephyr-lux|leafan":["wistella",1,49,"Temperate","Standard"],"helzephyr-lux|skutlass":["bulldosu",1,49,"Temperate","Standard"],"helzephyr-lux|vanwyrm-cryst":["bulldosu",1,49,"Temperate","Standard"],"helzephyr-lux|mossanda-lux":["suzaku",1,50,"Temperate","Standard"],"helzephyr-lux|shroomer-noct":["suzaku",1,50,"Temperate","Standard"],"helzephyr-lux|incineram":["quivern",1,50,"Temperate","Standard"],"helzephyr-lux|vaelet":["azurobe-cryst",1,50,"Temperate","Standard"],"helzephyr-lux|wixen-noct":["azurobe-cryst",1,50,"Temperate","Standard"],"helzephyr-lux|snock-lux":["nitemary",1,51,"Temperate","Standard"],"helzephyr-lux|prixter":["nitemary",1,51,"Temperate","Standard"],"helzephyr-lux|shroomer":["palumba",1,51,"Temperate","Standard"],"helzephyr-lux|kingpaca-cryst":["palumba",1,51,"Temperate","Standard"],"helzephyr-lux|needoll-noct":["blazehowl-noct",1,52,"Temperate","Standard"],"helzephyr-lux|skutlass-ignis":["blazehowl-noct",1,52,"Temperate","Standard"],"helzephyr-lux|rayhound-cryst":["warsect",1,52,"Temperate","Standard"],"helzephyr-lux|smokie-cryst":["warsect",1,53,"Temperate","Standard"],"helzephyr-lux|vanwyrm":["quivern-botan",1,53,"Temperate","Standard"],"helzephyr-lux|polapup":["incineram-noct",1,54,"Temperate","Standard"],"helzephyr-lux|kitsun":["incineram-noct",1,54,"Temperate","Standard"],"helzephyr-lux|lapiron":["nitemary-botan",1,54,"Temperate","Standard"],"helzephyr-lux|maraith":["turtacle-terra",1,55,"Temperate","Standard"],"helzephyr-lux|petallia":["mammorest",1,55,"Temperate","Standard"],"helzephyr-lux|tarantriss":["mammorest",1,55,"Temperate","Standard"],"helzephyr-lux|mimog":["tropicaw",1,55,"Temperate","Standard"],"helzephyr-lux|slowatt":["tropicaw",1,55,"Temperate","Standard"],"helzephyr-lux|smokie":["blazehowl",1,55,"Temperate","Standard"],"helzephyr-lux|hoodle":["blazehowl",1,56,"Temperate","Standard"],"helzephyr-lux|snock":["solmora",1,56,"Temperate","Standard"],"helzephyr-lux|katress-ignis":["broncherry",1,56,"Temperate","Standard"],"helzephyr-lux|sibelyx":["broncherry",1,56,"Temperate","Standard"],"helzephyr-lux|xenovader":["prunelia",1,57,"Temperate","Standard"],"helzephyr-lux|surfent-terra":["dynamoff",1,57,"Temperate","Standard"],"helzephyr-lux|penking-lux":["dynamoff",1,57,"Temperate","Standard"],"helzephyr-lux|pyrin-noct":["leafan",1,57,"Temperate","Standard"],"helzephyr-lux|valentail":["vanwyrm-cryst",1,58,"Temperate","Standard"],"helzephyr-lux|rayhound":["mossanda-lux",1,58,"Temperate","Standard"],"helzephyr-lux|reindrix":["mossanda-lux",1,59,"Temperate","Standard"],"helzephyr-lux|pyrin":["incineram",1,60,"Temperate","Standard"],"helzephyr-lux|lullu":["incineram",1,60,"Temperate","Standard"],"helzephyr-lux|lunaris":["vaelet",1,60,"Temperate","Standard"],"helzephyr-lux|woolipop-terra":["wixen-noct",1,60,"Temperate","Standard"],"helzephyr-lux|katress":["snock-lux",1,61,"Temperate","Standard"],"helzephyr-lux|robinquill-terra":["snock-lux",1,61,"Temperate","Standard"],"helzephyr-lux|mossanda":["prixter",1,61,"Temperate","Standard"],"helzephyr-lux|penking":["prixter",1,61,"Temperate","Standard"],"helzephyr-lux|wixen":["shroomer",1,61,"Temperate","Standard"],"helzephyr-lux|lovander":["shroomer",1,62,"Temperate","Standard"],"helzephyr-lux|loupmoon":["kingpaca-cryst",1,62,"Temperate","Standard"],"helzephyr-lux|munchill":["bakemi",1,62,"Temperate","Standard"],"helzephyr-lux|sweepa":["digtoise",1,63,"Temperate","Standard"],"helzephyr-lux|kingpaca":["skutlass-ignis",1,64,"Temperate","Standard"],"helzephyr-lux|yakumo":["skutlass-ignis",1,64,"Temperate","Standard"],"helzephyr-lux|wispaw":["rayhound-cryst",1,65,"Temperate","Standard"],"helzephyr-lux|robinquill":["smokie-cryst",1,65,"Temperate","Standard"],"helzephyr-lux|univolt":["smokie-cryst",1,65,"Temperate","Standard"],"helzephyr-lux|kikit":["gloopie-primo",1,66,"Temperate","Standard"],"helzephyr-lux|tombat":["vanwyrm",1,66,"Temperate","Standard"],"helzephyr-lux|puffolt":["polapup",1,67,"Temperate","Standard"],"helzephyr-lux|snugloo":["kitsun",1,67,"Temperate","Standard"],"helzephyr-lux|turtacle":["lapiron",1,68,"Temperate","Standard"],"helzephyr-lux|needoll":["beakon",1,68,"Temperate","Standard"],"helzephyr-lux|surfent":["carnibora",1,68,"Temperate","Standard"],"helzephyr-lux|ribbuny-botan":["maraith",1,68,"Temperate","Standard"],"helzephyr-lux|kelpsea-ignis":["maraith",1,69,"Temperate","Standard"],"helzephyr-lux|muffly":["petallia",1,69,"Temperate","Standard"],"helzephyr-lux|pengullet-lux":["petallia",1,69,"Temperate","Standard"],"hangyu-cryst|helzephyr-lux":["tarantriss",1,69,"Temperate","Standard"],"helzephyr-lux|killamari-primo":["slowatt",1,70,"Temperate","Standard"],"helzephyr-lux|nitewing":["smokie",1,70,"Temperate","Standard"],"helzephyr-lux|jellroy":["hoodle",1,71,"Temperate","Standard"],"helzephyr-lux|herbil":["elizabee",1,72,"Temperate","Standard"],"helzephyr-lux|leezpunk-ignis":["katress-ignis",1,72,"Temperate","Standard"],"helzephyr-lux|jelliette":["katress-ignis",1,72,"Temperate","Standard"],"helzephyr-lux|leezpunk":["sibelyx",1,72,"Temperate","Standard"],"helzephyr-lux|melpaca":["surfent-terra",1,73,"Temperate","Standard"],"helzephyr-lux|tocotoco":["surfent-terra",1,73,"Temperate","Standard"],"helzephyr-lux|mau-cryst":["penking-lux",1,74,"Temperate","Standard"],"helzephyr-lux|killamari":["croajiro-noct",1,74,"Temperate","Standard"],"hangyu|helzephyr-lux":["pyrin-noct",1,74,"Temperate","Standard"],"helzephyr-lux|mozzarina":["gorirat-terra",1,75,"Temperate","Standard"],"helzephyr-lux|kelpsea":["gorirat-terra",1,75,"Temperate","Standard"],"helzephyr-lux|woolipop":["dinossom-lux",1,75,"Temperate","Standard"],"helzephyr-lux|tanzee-ignis":["dinossom-lux",1,75,"Temperate","Standard"],"helzephyr-lux|swee":["valentail",1,75,"Temperate","Standard"],"helzephyr-lux|jolthog-cryst":["valentail",1,76,"Temperate","Standard"],"helzephyr-lux|ribbuny":["dazzi-noct",1,76,"Temperate","Standard"],"helzephyr-lux|rooby":["dazzi-noct",1,76,"Temperate","Standard"],"helzephyr-lux|rushoar":["rayhound",1,76,"Temperate","Standard"],"helzephyr-lux|tanzee":["reindrix",1,77,"Temperate","Standard"],"helzephyr-lux|nox":["caprity-noct",1,77,"Temperate","Standard"],"helzephyr-lux|pupperai":["caprity-noct",1,77,"Temperate","Standard"],"helzephyr-lux|hoocrates":["chillet-ignis",1,77,"Temperate","Standard"],"helzephyr-lux|pengullet":["fenglope",1,78,"Temperate","Standard"],"helzephyr-lux|sparkit":["pyrin",1,79,"Temperate","Standard"],"helzephyr-lux|lifmunk":["lullu",1,79,"Temperate","Standard"],"helzephyr-lux|jolthog":["lullu",1,79,"Temperate","Standard"],"helzephyr-lux|mau":["lullu",1,79,"Temperate","Standard"],"helzephyr-lux|lamball":["lunaris",1,79,"Temperate","Standard"],"helzephyr-lux|vixy":["lunaris",1,80,"Temperate","Standard"],"helzephyr-lux|teafant":["lunaris",1,80,"Temperate","Standard"],"helzephyr-lux|illuminant-bat":["woolipop-terra",1,80,"Temperate","Standard"],"helzephyr-lux|illuminant-slime":["woolipop-terra",1,80,"Temperate","Standard"],"helzephyr-lux|purple-slime":["woolipop-terra",1,80,"Temperate","Standard"],"helzephyr-lux|rainbow-slime":["woolipop-terra",1,80,"Temperate","Standard"],"helzephyr-lux|red-slime":["woolipop-terra",1,80,"Temperate","Standard"],"helzephyr|venusa":["ragnahawk",1,44,"Temperate","Standard"],"hoodle|venusa":["solmora",1,56,"Temperate","Standard"],"hangyu-cryst|venusa":["mimog",1,70,"Temperate","Standard"],"herbil|venusa":["katress-ignis",1,72,"Temperate","Standard"],"hangyu|venusa":["pyrin-noct",1,75,"Temperate","Standard"],"hoocrates|venusa":["chillet-ignis",1,78,"Temperate","Standard"],"helzephyr|sootseer":["ragnahawk",1,44,"Temperate","Standard"],"hoodle|sootseer":["solmora",1,56,"Temperate","Standard"],"hangyu-cryst|sootseer":["mimog",1,70,"Temperate","Standard"],"herbil|sootseer":["katress-ignis",1,72,"Temperate","Standard"],"hangyu|sootseer":["gorirat-terra",1,75,"Temperate","Standard"],"hoocrates|sootseer":["fenglope",1,78,"Temperate","Standard"],"helzephyr|xenogard":["reptyro",1,44,"Temperate","Standard"],"hoodle|xenogard":["broncherry",1,56,"Temperate","Standard"],"hangyu-cryst|xenogard":["slowatt",1,70,"Temperate","Standard"],"herbil|xenogard":["sibelyx",1,72,"Temperate","Standard"],"hangyu|xenogard":["gorirat-terra",1,75,"Temperate","Standard"],"hoocrates|xenogard":["fenglope",1,78,"Temperate","Standard"],"helzephyr|majex":["mammorest-cryst",1,45,"Temperate","Standard"],"hoodle|majex":["prunelia",1,57,"Temperate","Standard"],"hangyu-cryst|majex":["smokie",1,70,"Temperate","Standard"],"herbil|majex":["xenovader",1,73,"Temperate","Standard"],"hangyu|majex":["dinossom-lux",1,75,"Temperate","Standard"],"hoocrates|majex":["foxcicle",1,78,"Temperate","Standard"],"helzephyr|ragnahawk":["relaxaurus",1,45,"Temperate","Standard"],"hoodle|ragnahawk":["leafan",1,57,"Temperate","Standard"],"hangyu-cryst|ragnahawk":["snock",1,71,"Temperate","Standard"],"herbil|ragnahawk":["surfent-terra",1,73,"Temperate","Standard"],"hangyu|ragnahawk":["dazzi-noct",1,76,"Temperate","Standard"],"hoocrates|ragnahawk":["lullu",1,79,"Temperate","Standard"],"helzephyr|reptyro":["relaxaurus",1,46,"Temperate","Standard"],"hoodle|reptyro":["leafan",1,57,"Temperate","Standard"],"hangyu-cryst|reptyro":["snock",1,71,"Temperate","Standard"],"herbil|reptyro":["surfent-terra",1,73,"Temperate","Standard"],"hangyu|reptyro":["rayhound",1,76,"Temperate","Standard"],"hoocrates|reptyro":["lullu",1,79,"Temperate","Standard"],"helzephyr|mammorest-cryst":["polapup-terra",1,46,"Temperate","Standard"],"hoodle|mammorest-cryst":["skutlass",1,58,"Temperate","Standard"],"hangyu-cryst|mammorest-cryst":["elizabee",1,71,"Temperate","Standard"],"herbil|mammorest-cryst":["penking-lux",1,74,"Temperate","Standard"],"hangyu|mammorest-cryst":["rayhound",1,76,"Temperate","Standard"],"hoocrates|mammorest-cryst":["lunaris",1,79,"Temperate","Standard"],"helzephyr|relaxaurus":["pierdon",1,46,"Temperate","Standard"],"hoodle|relaxaurus":["vanwyrm-cryst",1,58,"Temperate","Standard"],"hangyu-cryst|relaxaurus":["katress-ignis",1,72,"Temperate","Standard"],"herbil|relaxaurus":["croajiro-noct",1,74,"Temperate","Standard"],"hangyu|relaxaurus":["reindrix",1,77,"Temperate","Standard"],"hoocrates|relaxaurus":["lunaris",1,80,"Temperate","Standard"],"helzephyr|polapup-terra":["pierdon",1,46,"Temperate","Standard"],"hoodle|polapup-terra":["vanwyrm-cryst",1,58,"Temperate","Standard"],"hangyu-cryst|polapup-terra":["katress-ignis",1,72,"Temperate","Standard"],"herbil|polapup-terra":["croajiro-noct",1,74,"Temperate","Standard"],"hangyu|polapup-terra":["caprity-noct",1,77,"Temperate","Standard"],"hoocrates|polapup-terra":["elgrove",1,80,"Temperate","Standard"],"helzephyr|pierdon":["menasting",1,47,"Temperate","Standard"],"hoodle|pierdon":["mossanda-lux",1,58,"Temperate","Standard"],"hangyu-cryst|pierdon":["sibelyx",1,72,"Temperate","Standard"],"herbil|pierdon":["pyrin-noct",1,74,"Temperate","Standard"],"hangyu|pierdon":["caprity-noct",1,77,"Temperate","Standard"],"hoocrates|pierdon":["elgrove",1,80,"Temperate","Standard"],"helzephyr|menasting":["pierdon",1,47,"Temperate","Standard"],"hoodle|menasting":["mossanda-lux",1,59,"Temperate","Standard"],"hangyu-cryst|menasting":["sibelyx",1,72,"Temperate","Standard"],"herbil|menasting":["pyrin-noct",1,75,"Temperate","Standard"],"hangyu|menasting":["chillet-ignis",1,77,"Temperate","Standard"],"hoocrates|menasting":["woolipop-terra",1,80,"Temperate","Standard"],"helzephyr|helzephyr":["menasting",1,47,"Temperate","Standard"],"helzephyr|omascul":["menasting",1,47,"Temperate","Standard"],"helzephyr|starryon":["omascul",1,47,"Temperate","Standard"],"helzephyr|verdash":["omascul",1,47,"Temperate","Standard"],"helzephyr|wistella":["starryon",1,48,"Temperate","Standard"],"helzephyr|suzaku":["verdash",1,48,"Temperate","Standard"],"helzephyr|quivern":["gildra",1,48,"Temperate","Standard"],"helzephyr|nitemary":["wistella",1,49,"Temperate","Standard"],"helzephyr|palumba":["wistella",1,49,"Temperate","Standard"],"helzephyr|nyafia":["bulldosu",1,49,"Temperate","Standard"],"helzephyr|icelyn":["bulldosu",1,49,"Temperate","Standard"],"helzephyr|warsect":["suzaku",1,50,"Temperate","Standard"],"helzephyr|loupmoon-cryst":["quivern",1,50,"Temperate","Standard"],"helzephyr|quivern-botan":["quivern",1,50,"Temperate","Standard"],"helzephyr|incineram-noct":["azurobe-cryst",1,50,"Temperate","Standard"],"helzephyr|nitemary-botan":["azurobe-cryst",1,50,"Temperate","Standard"],"helzephyr|turtacle-terra":["nitemary",1,51,"Temperate","Standard"],"helzephyr|mammorest":["nitemary",1,51,"Temperate","Standard"],"helzephyr|tropicaw":["palumba",1,51,"Temperate","Standard"],"helzephyr|solmora":["nyafia",1,51,"Temperate","Standard"],"helzephyr|prunelia":["icelyn",1,52,"Temperate","Standard"],"helzephyr|leafan":["blazehowl-noct",1,52,"Temperate","Standard"],"helzephyr|skutlass":["blazehowl-noct",1,52,"Temperate","Standard"],"helzephyr|vanwyrm-cryst":["warsect",1,52,"Temperate","Standard"],"helzephyr|mossanda-lux":["warsect",1,53,"Temperate","Standard"],"helzephyr|shroomer-noct":["loupmoon-cryst",1,53,"Temperate","Standard"],"helzephyr|incineram":["quivern-botan",1,53,"Temperate","Standard"],"helzephyr|vaelet":["quivern-botan",1,53,"Temperate","Standard"],"helzephyr|wixen-noct":["incineram-noct",1,54,"Temperate","Standard"],"helzephyr|snock-lux":["incineram-noct",1,54,"Temperate","Standard"],"helzephyr|prixter":["nitemary-botan",1,54,"Temperate","Standard"],"helzephyr|shroomer":["nitemary-botan",1,54,"Temperate","Standard"],"helzephyr|kingpaca-cryst":["turtacle-terra",1,54,"Temperate","Standard"],"helzephyr|needoll-noct":["tropicaw",1,55,"Temperate","Standard"],"helzephyr|skutlass-ignis":["blazehowl",1,55,"Temperate","Standard"],"helzephyr|rayhound-cryst":["blazehowl",1,56,"Temperate","Standard"],"helzephyr|smokie-cryst":["solmora",1,56,"Temperate","Standard"],"helzephyr|vanwyrm":["prunelia",1,57,"Temperate","Standard"],"helzephyr|polapup":["prunelia",1,57,"Temperate","Standard"],"helzephyr|kitsun":["dynamoff",1,57,"Temperate","Standard"],"helzephyr|lapiron":["dynamoff",1,57,"Temperate","Standard"],"helzephyr|maraith":["skutlass",1,58,"Temperate","Standard"],"helzephyr|petallia":["skutlass",1,58,"Temperate","Standard"],"helzephyr|tarantriss":["vanwyrm-cryst",1,58,"Temperate","Standard"],"helzephyr|mimog":["vanwyrm-cryst",1,58,"Temperate","Standard"],"helzephyr|slowatt":["mossanda-lux",1,58,"Temperate","Standard"],"helzephyr|smokie":["mossanda-lux",1,59,"Temperate","Standard"],"helzephyr|hoodle":["shroomer-noct",1,59,"Temperate","Standard"],"helzephyr|snock":["shroomer-noct",1,59,"Temperate","Standard"],"helzephyr|katress-ignis":["dogen",1,59,"Temperate","Standard"],"helzephyr|sibelyx":["incineram",1,60,"Temperate","Standard"],"helzephyr|xenovader":["incineram",1,60,"Temperate","Standard"],"helzephyr|surfent-terra":["vaelet",1,60,"Temperate","Standard"],"helzephyr|penking-lux":["wixen-noct",1,60,"Temperate","Standard"],"helzephyr|pyrin-noct":["snock-lux",1,61,"Temperate","Standard"],"helzephyr|valentail":["prixter",1,61,"Temperate","Standard"],"helzephyr|rayhound":["shroomer",1,62,"Temperate","Standard"],"helzephyr|reindrix":["kingpaca-cryst",1,62,"Temperate","Standard"],"helzephyr|pyrin":["digtoise",1,63,"Temperate","Standard"],"helzephyr|lullu":["bushi",1,63,"Temperate","Standard"],"helzephyr|lunaris":["felbat",1,63,"Temperate","Standard"],"helzephyr|woolipop-terra":["needoll-noct",1,64,"Temperate","Standard"],"helzephyr|katress":["needoll-noct",1,64,"Temperate","Standard"],"helzephyr|robinquill-terra":["skutlass-ignis",1,64,"Temperate","Standard"],"helzephyr|mossanda":["skutlass-ignis",1,64,"Temperate","Standard"],"helzephyr|penking":["rayhound-cryst",1,64,"Temperate","Standard"],"helzephyr|wixen":["rayhound-cryst",1,65,"Temperate","Standard"],"helzephyr|lovander":["smokie-cryst",1,65,"Temperate","Standard"],"helzephyr|loupmoon":["dumud-gild",1,65,"Temperate","Standard"],"helzephyr|munchill":["gloopie-primo",1,65,"Temperate","Standard"],"helzephyr|sweepa":["elphidran-aqua",1,66,"Temperate","Standard"],"helzephyr|kingpaca":["kitsun",1,67,"Temperate","Standard"],"helzephyr|yakumo":["lapiron",1,67,"Temperate","Standard"],"helzephyr|wispaw":["beakon",1,68,"Temperate","Standard"],"helzephyr|robinquill":["beakon",1,68,"Temperate","Standard"],"helzephyr|univolt":["carnibora",1,68,"Temperate","Standard"],"helzephyr|kikit":["petallia",1,69,"Temperate","Standard"],"helzephyr|tombat":["tarantriss",1,69,"Temperate","Standard"],"helzephyr|puffolt":["mimog",1,70,"Temperate","Standard"],"helzephyr|snugloo":["smokie",1,70,"Temperate","Standard"],"helzephyr|turtacle":["hoodle",1,71,"Temperate","Standard"],"helzephyr|needoll":["hoodle",1,71,"Temperate","Standard"],"helzephyr|surfent":["snock",1,71,"Temperate","Standard"],"helzephyr|ribbuny-botan":["elizabee",1,72,"Temperate","Standard"],"helzephyr|kelpsea-ignis":["katress-ignis",1,72,"Temperate","Standard"],"helzephyr|muffly":["katress-ignis",1,72,"Temperate","Standard"],"helzephyr|pengullet-lux":["sibelyx",1,72,"Temperate","Standard"],"hangyu-cryst|helzephyr":["xenovader",1,73,"Temperate","Standard"],"helzephyr|killamari-primo":["azurobe",1,73,"Temperate","Standard"],"helzephyr|nitewing":["surfent-terra",1,73,"Temperate","Standard"],"helzephyr|jellroy":["croajiro-noct",1,74,"Temperate","Standard"],"helzephyr|herbil":["gorirat-terra",1,75,"Temperate","Standard"],"helzephyr|leezpunk-ignis":["gorirat-terra",1,75,"Temperate","Standard"],"helzephyr|jelliette":["dinossom-lux",1,75,"Temperate","Standard"],"helzephyr|leezpunk":["valentail",1,75,"Temperate","Standard"],"helzephyr|melpaca":["rayhound",1,76,"Temperate","Standard"],"helzephyr|tocotoco":["reindrix",1,77,"Temperate","Standard"],"helzephyr|mau-cryst":["caprity-noct",1,77,"Temperate","Standard"],"helzephyr|killamari":["chillet-ignis",1,77,"Temperate","Standard"],"hangyu|helzephyr":["chillet-ignis",1,78,"Temperate","Standard"],"helzephyr|mozzarina":["fenglope",1,78,"Temperate","Standard"],"helzephyr|kelpsea":["foxcicle",1,78,"Temperate","Standard"],"helzephyr|woolipop":["foxcicle",1,78,"Temperate","Standard"],"helzephyr|tanzee-ignis":["pyrin",1,78,"Temperate","Standard"],"helzephyr|swee":["pyrin",1,79,"Temperate","Standard"],"helzephyr|jolthog-cryst":["lullu",1,79,"Temperate","Standard"],"helzephyr|ribbuny":["lullu",1,79,"Temperate","Standard"],"helzephyr|rooby":["lullu",1,79,"Temperate","Standard"],"helzephyr|rushoar":["lunaris",1,79,"Temperate","Standard"],"helzephyr|tanzee":["lunaris",1,80,"Temperate","Standard"],"helzephyr|nox":["elgrove",1,80,"Temperate","Standard"],"helzephyr|pupperai":["woolipop-terra",1,80,"Temperate","Standard"],"helzephyr|hoocrates":["woolipop-terra",1,80,"Temperate","Standard"],"helzephyr|pengullet":["katress",1,81,"Temperate","Standard"],"helzephyr|sparkit":["penking",1,82,"Temperate","Standard"],"helzephyr|lifmunk":["penking",1,82,"Temperate","Standard"],"helzephyr|jolthog":["wixen",1,82,"Temperate","Standard"],"helzephyr|mau":["wixen",1,82,"Temperate","Standard"],"helzephyr|lamball":["lovander",1,83,"Temperate","Standard"],"helzephyr|vixy":["lovander",1,83,"Temperate","Standard"],"helzephyr|teafant":["dinossom",1,83,"Temperate","Standard"],"helzephyr|illuminant-bat":["loupmoon",1,83,"Temperate","Standard"],"helzephyr|illuminant-slime":["loupmoon",1,83,"Temperate","Standard"],"helzephyr|purple-slime":["loupmoon",1,83,"Temperate","Standard"],"helzephyr|rainbow-slime":["loupmoon",1,83,"Temperate","Standard"],"helzephyr|red-slime":["loupmoon",1,83,"Temperate","Standard"],"hoodle|omascul":["shroomer-noct",1,59,"Temperate","Standard"],"hangyu-cryst|omascul":["xenovader",1,73,"Temperate","Standard"],"herbil|omascul":["gorirat-terra",1,75,"Temperate","Standard"],"hangyu|omascul":["fenglope",1,78,"Temperate","Standard"],"hoocrates|omascul":["katress",1,81,"Temperate","Standard"],"hoodle|starryon":["dogen",1,59,"Temperate","Standard"],"hangyu-cryst|starryon":["azurobe",1,73,"Temperate","Standard"],"herbil|starryon":["dinossom-lux",1,75,"Temperate","Standard"],"hangyu|starryon":["fenglope",1,78,"Temperate","Standard"],"hoocrates|starryon":["katress",1,81,"Temperate","Standard"],"hoodle|verdash":["dogen",1,59,"Temperate","Standard"],"hangyu-cryst|verdash":["azurobe",1,73,"Temperate","Standard"],"herbil|verdash":["dinossom-lux",1,75,"Temperate","Standard"],"hangyu|verdash":["foxcicle",1,78,"Temperate","Standard"],"hoocrates|verdash":["robinquill-terra",1,81,"Temperate","Standard"],"hoodle|wistella":["incineram",1,60,"Temperate","Standard"],"hangyu-cryst|wistella":["surfent-terra",1,73,"Temperate","Standard"],"herbil|wistella":["valentail",1,76,"Temperate","Standard"],"hangyu|wistella":["pyrin",1,78,"Temperate","Standard"],"hoocrates|wistella":["mossanda",1,81,"Temperate","Standard"],"hoodle|suzaku":["vaelet",1,60,"Temperate","Standard"],"hangyu-cryst|suzaku":["penking-lux",1,74,"Temperate","Standard"],"herbil|suzaku":["dazzi-noct",1,76,"Temperate","Standard"],"hangyu|suzaku":["lullu",1,79,"Temperate","Standard"],"hoocrates|suzaku":["penking",1,82,"Temperate","Standard"],"hoodle|quivern":["wixen-noct",1,60,"Temperate","Standard"],"hangyu-cryst|quivern":["croajiro-noct",1,74,"Temperate","Standard"],"herbil|quivern":["rayhound",1,76,"Temperate","Standard"],"hangyu|quivern":["lullu",1,79,"Temperate","Standard"],"hoocrates|quivern":["penking",1,82,"Temperate","Standard"],"hoodle|nitemary":["snock-lux",1,61,"Temperate","Standard"],"hangyu-cryst|nitemary":["pyrin-noct",1,74,"Temperate","Standard"],"herbil|nitemary":["reindrix",1,77,"Temperate","Standard"],"hangyu|nitemary":["lunaris",1,79,"Temperate","Standard"],"hoocrates|nitemary":["wixen",1,82,"Temperate","Standard"],"hoodle|palumba":["snock-lux",1,61,"Temperate","Standard"],"hangyu-cryst|palumba":["pyrin-noct",1,75,"Temperate","Standard"],"herbil|palumba":["reindrix",1,77,"Temperate","Standard"],"hangyu|palumba":["lunaris",1,80,"Temperate","Standard"],"hoocrates|palumba":["lovander",1,83,"Temperate","Standard"],"hoodle|nyafia":["prixter",1,61,"Temperate","Standard"],"hangyu-cryst|nyafia":["gorirat-terra",1,75,"Temperate","Standard"],"herbil|nyafia":["caprity-noct",1,77,"Temperate","Standard"],"hangyu|nyafia":["lunaris",1,80,"Temperate","Standard"],"hoocrates|nyafia":["lovander",1,83,"Temperate","Standard"],"hoodle|icelyn":["prixter",1,61,"Temperate","Standard"],"hangyu-cryst|icelyn":["gorirat-terra",1,75,"Temperate","Standard"],"herbil|icelyn":["caprity-noct",1,77,"Temperate","Standard"],"hangyu|icelyn":["elgrove",1,80,"Temperate","Standard"],"hoocrates|icelyn":["dinossom",1,83,"Temperate","Standard"],"hoodle|warsect":["shroomer",1,62,"Temperate","Standard"],"hangyu-cryst|warsect":["dinossom-lux",1,75,"Temperate","Standard"],"herbil|warsect":["chillet-ignis",1,78,"Temperate","Standard"],"hangyu|warsect":["woolipop-terra",1,80,"Temperate","Standard"],"hoocrates|warsect":["loupmoon",1,83,"Temperate","Standard"],"hoodle|loupmoon-cryst":["kingpaca-cryst",1,62,"Temperate","Standard"],"hangyu-cryst|loupmoon-cryst":["valentail",1,75,"Temperate","Standard"],"herbil|loupmoon-cryst":["fenglope",1,78,"Temperate","Standard"],"hangyu|loupmoon-cryst":["woolipop-terra",1,80,"Temperate","Standard"],"hoocrates|loupmoon-cryst":["loupmoon",1,83,"Temperate","Standard"],"hoodle|quivern-botan":["kingpaca-cryst",1,62,"Temperate","Standard"],"hangyu-cryst|quivern-botan":["valentail",1,76,"Temperate","Standard"],"herbil|quivern-botan":["fenglope",1,78,"Temperate","Standard"],"hangyu|quivern-botan":["katress",1,81,"Temperate","Standard"],"hoocrates|quivern-botan":["grintale",1,84,"Temperate","Standard"],"hoodle|incineram-noct":["bakemi",1,62,"Temperate","Standard"],"hangyu-cryst|incineram-noct":["dazzi-noct",1,76,"Temperate","Standard"],"herbil|incineram-noct":["foxcicle",1,78,"Temperate","Standard"],"hangyu|incineram-noct":["katress",1,81,"Temperate","Standard"],"hoocrates|incineram-noct":["grintale",1,84,"Temperate","Standard"],"hoodle|nitemary-botan":["bakemi",1,62,"Temperate","Standard"],"hangyu-cryst|nitemary-botan":["dazzi-noct",1,76,"Temperate","Standard"],"herbil|nitemary-botan":["foxcicle",1,78,"Temperate","Standard"],"hangyu|nitemary-botan":["robinquill-terra",1,81,"Temperate","Standard"],"hoocrates|nitemary-botan":["munchill",1,84,"Temperate","Standard"],"hoodle|turtacle-terra":["digtoise",1,62,"Temperate","Standard"],"hangyu-cryst|turtacle-terra":["rayhound",1,76,"Temperate","Standard"],"herbil|turtacle-terra":["pyrin",1,78,"Temperate","Standard"],"hangyu|turtacle-terra":["robinquill-terra",1,81,"Temperate","Standard"],"hoocrates|turtacle-terra":["munchill",1,84,"Temperate","Standard"],"hoodle|mammorest":["digtoise",1,63,"Temperate","Standard"],"hangyu-cryst|mammorest":["rayhound",1,76,"Temperate","Standard"],"herbil|mammorest":["pyrin",1,79,"Temperate","Standard"],"hangyu|mammorest":["mossanda",1,81,"Temperate","Standard"],"hoocrates|mammorest":["gorirat",1,84,"Temperate","Standard"],"hoodle|tropicaw":["bushi",1,63,"Temperate","Standard"],"hangyu-cryst|tropicaw":["reindrix",1,77,"Temperate","Standard"],"herbil|tropicaw":["lullu",1,79,"Temperate","Standard"],"hangyu|tropicaw":["mossanda",1,82,"Temperate","Standard"],"hoocrates|tropicaw":["gorirat",1,85,"Temperate","Standard"],"hoodle|solmora":["felbat",1,63,"Temperate","Standard"],"hangyu-cryst|solmora":["caprity-noct",1,77,"Temperate","Standard"],"herbil|solmora":["lullu",1,79,"Temperate","Standard"],"hangyu|solmora":["penking",1,82,"Temperate","Standard"],"hoocrates|solmora":["sweepa",1,85,"Temperate","Standard"],"hoodle|prunelia":["needoll-noct",1,64,"Temperate","Standard"],"hangyu-cryst|prunelia":["chillet-ignis",1,77,"Temperate","Standard"],"herbil|prunelia":["lunaris",1,80,"Temperate","Standard"],"hangyu|prunelia":["wixen",1,82,"Temperate","Standard"],"hoocrates|prunelia":["sweepa",1,85,"Temperate","Standard"],"hoodle|leafan":["skutlass-ignis",1,64,"Temperate","Standard"],"hangyu-cryst|leafan":["fenglope",1,78,"Temperate","Standard"],"herbil|leafan":["elgrove",1,80,"Temperate","Standard"],"hangyu|leafan":["lovander",1,83,"Temperate","Standard"],"hoocrates|leafan":["sweepa",1,86,"Temperate","Standard"],"hoodle|skutlass":["skutlass-ignis",1,64,"Temperate","Standard"],"hangyu-cryst|skutlass":["fenglope",1,78,"Temperate","Standard"],"herbil|skutlass":["elgrove",1,80,"Temperate","Standard"],"hangyu|skutlass":["dinossom",1,83,"Temperate","Standard"],"hoocrates|skutlass":["sweepa",1,86,"Temperate","Standard"],"hoodle|vanwyrm-cryst":["rayhound-cryst",1,64,"Temperate","Standard"],"hangyu-cryst|vanwyrm-cryst":["foxcicle",1,78,"Temperate","Standard"],"herbil|vanwyrm-cryst":["woolipop-terra",1,80,"Temperate","Standard"],"hangyu|vanwyrm-cryst":["dinossom",1,83,"Temperate","Standard"],"hoocrates|vanwyrm-cryst":["dazemu",1,86,"Temperate","Standard"],"hoodle|mossanda-lux":["rayhound-cryst",1,65,"Temperate","Standard"],"hangyu-cryst|mossanda-lux":["foxcicle",1,78,"Temperate","Standard"],"herbil|mossanda-lux":["woolipop-terra",1,80,"Temperate","Standard"],"hangyu|mossanda-lux":["loupmoon",1,83,"Temperate","Standard"],"hoocrates|mossanda-lux":["dazemu",1,86,"Temperate","Standard"],"hoodle|shroomer-noct":["smokie-cryst",1,65,"Temperate","Standard"],"hangyu-cryst|shroomer-noct":["pyrin",1,78,"Temperate","Standard"],"herbil|shroomer-noct":["katress",1,81,"Temperate","Standard"],"hangyu|shroomer-noct":["loupmoon",1,83,"Temperate","Standard"],"hoocrates|shroomer-noct":["dazemu",1,86,"Temperate","Standard"],"hoodle|incineram":["dumud-gild",1,65,"Temperate","Standard"],"hangyu-cryst|incineram":["lullu",1,79,"Temperate","Standard"],"herbil|incineram":["robinquill-terra",1,81,"Temperate","Standard"],"hangyu|incineram":["grintale",1,84,"Temperate","Standard"],"hoocrates|incineram":["dazemu",1,87,"Temperate","Standard"],"hoodle|vaelet":["dumud-gild",1,65,"Temperate","Standard"],"hangyu-cryst|vaelet":["lullu",1,79,"Temperate","Standard"],"herbil|vaelet":["robinquill-terra",1,81,"Temperate","Standard"],"hangyu|vaelet":["munchill",1,84,"Temperate","Standard"],"hoocrates|vaelet":["dazemu",1,87,"Temperate","Standard"],"hoodle|wixen-noct":["gloopie-primo",1,65,"Temperate","Standard"],"hangyu-cryst|wixen-noct":["lullu",1,79,"Temperate","Standard"],"herbil|wixen-noct":["mossanda",1,81,"Temperate","Standard"],"hangyu|wixen-noct":["munchill",1,84,"Temperate","Standard"],"hoocrates|wixen-noct":["dazemu",1,87,"Temperate","Standard"],"hoodle|snock-lux":["gloopie-primo",1,66,"Temperate","Standard"],"hangyu-cryst|snock-lux":["lunaris",1,79,"Temperate","Standard"],"herbil|snock-lux":["mossanda",1,82,"Temperate","Standard"],"hangyu|snock-lux":["gorirat",1,84,"Temperate","Standard"],"hoocrates|snock-lux":["kingpaca",1,87,"Temperate","Standard"],"hoodle|prixter":["elphidran-aqua",1,66,"Temperate","Standard"],"hangyu-cryst|prixter":["lunaris",1,80,"Temperate","Standard"],"herbil|prixter":["penking",1,82,"Temperate","Standard"],"hangyu|prixter":["gorirat",1,85,"Temperate","Standard"],"hoocrates|prixter":["kingpaca",1,88,"Temperate","Standard"],"hoodle|shroomer":["elphidran-aqua",1,66,"Temperate","Standard"],"hangyu-cryst|shroomer":["lunaris",1,80,"Temperate","Standard"],"herbil|shroomer":["penking",1,82,"Temperate","Standard"],"hangyu|shroomer":["sweepa",1,85,"Temperate","Standard"],"hoocrates|shroomer":["yakumo",1,88,"Temperate","Standard"],"hoodle|kingpaca-cryst":["vanwyrm",1,66,"Temperate","Standard"],"hangyu-cryst|kingpaca-cryst":["elgrove",1,80,"Temperate","Standard"],"herbil|kingpaca-cryst":["wixen",1,82,"Temperate","Standard"],"hangyu|kingpaca-cryst":["sweepa",1,85,"Temperate","Standard"],"hoocrates|kingpaca-cryst":["yakumo",1,88,"Temperate","Standard"],"hoodle|needoll-noct":["kitsun",1,67,"Temperate","Standard"],"hangyu-cryst|needoll-noct":["katress",1,81,"Temperate","Standard"],"herbil|needoll-noct":["dinossom",1,83,"Temperate","Standard"],"hangyu|needoll-noct":["sweepa",1,86,"Temperate","Standard"],"hoocrates|needoll-noct":["robinquill",1,89,"Temperate","Standard"],"hoodle|skutlass-ignis":["lapiron",1,67,"Temperate","Standard"],"hangyu-cryst|skutlass-ignis":["robinquill-terra",1,81,"Temperate","Standard"],"herbil|skutlass-ignis":["loupmoon",1,83,"Temperate","Standard"],"hangyu|skutlass-ignis":["dazemu",1,86,"Temperate","Standard"],"hoocrates|skutlass-ignis":["robinquill",1,89,"Temperate","Standard"],"hoodle|rayhound-cryst":["lapiron",1,68,"Temperate","Standard"],"hangyu-cryst|rayhound-cryst":["robinquill-terra",1,81,"Temperate","Standard"],"herbil|rayhound-cryst":["loupmoon",1,83,"Temperate","Standard"],"hangyu|rayhound-cryst":["dazemu",1,86,"Temperate","Standard"],"hoocrates|rayhound-cryst":["univolt",1,89,"Temperate","Standard"],"hoodle|smokie-cryst":["beakon",1,68,"Temperate","Standard"],"hangyu-cryst|smokie-cryst":["mossanda",1,81,"Temperate","Standard"],"herbil|smokie-cryst":["grintale",1,84,"Temperate","Standard"],"hangyu|smokie-cryst":["dazemu",1,86,"Temperate","Standard"],"hoocrates|smokie-cryst":["univolt",1,89,"Temperate","Standard"],"hoodle|vanwyrm":["maraith",1,68,"Temperate","Standard"],"hangyu-cryst|vanwyrm":["wixen",1,82,"Temperate","Standard"],"herbil|vanwyrm":["gorirat",1,84,"Temperate","Standard"],"hangyu|vanwyrm":["dazemu",1,87,"Temperate","Standard"],"hoocrates|vanwyrm":["dumud",1,90,"Temperate","Standard"],"hoodle|polapup":["maraith",1,69,"Temperate","Standard"],"hangyu-cryst|polapup":["wixen",1,82,"Temperate","Standard"],"herbil|polapup":["gorirat",1,85,"Temperate","Standard"],"hangyu|polapup":["kingpaca",1,87,"Temperate","Standard"],"hoocrates|polapup":["fuack-ignis",1,90,"Temperate","Standard"],"hoodle|kitsun":["petallia",1,69,"Temperate","Standard"],"hangyu-cryst|kitsun":["lovander",1,83,"Temperate","Standard"],"herbil|kitsun":["sweepa",1,85,"Temperate","Standard"],"hangyu|kitsun":["kingpaca",1,88,"Temperate","Standard"],"hoocrates|kitsun":["fuack-ignis",1,91,"Temperate","Standard"],"hoodle|lapiron":["petallia",1,69,"Temperate","Standard"],"hangyu-cryst|lapiron":["lovander",1,83,"Temperate","Standard"],"herbil|lapiron":["sweepa",1,85,"Temperate","Standard"],"hangyu|lapiron":["yakumo",1,88,"Temperate","Standard"],"hoocrates|lapiron":["kikit",1,91,"Temperate","Standard"],"hoodle|maraith":["mimog",1,70,"Temperate","Standard"],"hangyu-cryst|maraith":["loupmoon",1,83,"Temperate","Standard"],"herbil|maraith":["sweepa",1,86,"Temperate","Standard"],"hangyu|maraith":["finsider-ignis",1,88,"Temperate","Standard"],"hoocrates|maraith":["arsox",1,91,"Temperate","Standard"],"hoodle|petallia":["mimog",1,70,"Temperate","Standard"],"hangyu-cryst|petallia":["loupmoon",1,83,"Temperate","Standard"],"herbil|petallia":["sweepa",1,86,"Temperate","Standard"],"hangyu|petallia":["wispaw",1,88,"Temperate","Standard"],"hoocrates|petallia":["chillet",1,91,"Temperate","Standard"],"hoodle|tarantriss":["slowatt",1,70,"Temperate","Standard"],"hangyu-cryst|tarantriss":["grintale",1,84,"Temperate","Standard"],"herbil|tarantriss":["sweepa",1,86,"Temperate","Standard"],"hangyu|tarantriss":["wispaw",1,89,"Temperate","Standard"],"hoocrates|tarantriss":["chillet",1,92,"Temperate","Standard"],"hoodle|mimog":["slowatt",1,70,"Temperate","Standard"],"hangyu-cryst|mimog":["grintale",1,84,"Temperate","Standard"],"herbil|mimog":["dazemu",1,86,"Temperate","Standard"],"hangyu|mimog":["robinquill",1,89,"Temperate","Standard"],"hoocrates|mimog":["tombat",1,92,"Temperate","Standard"],"hoodle|slowatt":["smokie",1,70,"Temperate","Standard"],"hangyu-cryst|slowatt":["munchill",1,84,"Temperate","Standard"],"herbil|slowatt":["dazemu",1,86,"Temperate","Standard"],"hangyu|slowatt":["robinquill",1,89,"Temperate","Standard"],"hoocrates|slowatt":["tombat",1,92,"Temperate","Standard"],"hoodle|smokie":["slowatt",1,70,"Temperate","Standard"],"hangyu-cryst|smokie":["munchill",1,84,"Temperate","Standard"],"herbil|smokie":["dazemu",1,86,"Temperate","Standard"],"hangyu|smokie":["univolt",1,89,"Temperate","Standard"],"hoocrates|smokie":["beegarde",1,92,"Temperate","Standard"],"hoodle|hoodle":["smokie",1,71,"Temperate","Standard"],"hoodle|snock":["smokie",1,71,"Temperate","Standard"],"hoodle|katress-ignis":["snock",1,71,"Temperate","Standard"],"hoodle|sibelyx":["elizabee",1,71,"Temperate","Standard"],"hoodle|xenovader":["elizabee",1,72,"Temperate","Standard"],"hoodle|surfent-terra":["katress-ignis",1,72,"Temperate","Standard"],"hoodle|penking-lux":["sibelyx",1,72,"Temperate","Standard"],"hoodle|pyrin-noct":["xenovader",1,73,"Temperate","Standard"],"hoodle|valentail":["azurobe",1,73,"Temperate","Standard"],"hoodle|rayhound":["surfent-terra",1,73,"Temperate","Standard"],"hoodle|reindrix":["penking-lux",1,74,"Temperate","Standard"],"hoodle|pyrin":["pyrin-noct",1,75,"Temperate","Standard"],"hoodle|lullu":["gorirat-terra",1,75,"Temperate","Standard"],"hoodle|lunaris":["dinossom-lux",1,75,"Temperate","Standard"],"hoodle|woolipop-terra":["valentail",1,75,"Temperate","Standard"],"hoodle|katress":["valentail",1,76,"Temperate","Standard"],"hoodle|robinquill-terra":["dazzi-noct",1,76,"Temperate","Standard"],"hoodle|mossanda":["dazzi-noct",1,76,"Temperate","Standard"],"hoodle|penking":["rayhound",1,76,"Temperate","Standard"],"hoodle|wixen":["rayhound",1,76,"Temperate","Standard"],"hoodle|lovander":["reindrix",1,77,"Temperate","Standard"],"hoodle|loupmoon":["caprity-noct",1,77,"Temperate","Standard"],"hoodle|munchill":["chillet-ignis",1,77,"Temperate","Standard"],"hoodle|sweepa":["fenglope",1,78,"Temperate","Standard"],"hoodle|kingpaca":["lullu",1,79,"Temperate","Standard"],"hoodle|yakumo":["lullu",1,79,"Temperate","Standard"],"hoodle|wispaw":["lunaris",1,80,"Temperate","Standard"],"hoodle|robinquill":["lunaris",1,80,"Temperate","Standard"],"hoodle|univolt":["elgrove",1,80,"Temperate","Standard"],"hoodle|kikit":["katress",1,81,"Temperate","Standard"],"hoodle|tombat":["robinquill-terra",1,81,"Temperate","Standard"],"hoodle|puffolt":["mossanda",1,82,"Temperate","Standard"],"hoodle|snugloo":["wixen",1,82,"Temperate","Standard"],"hoodle|turtacle":["lovander",1,83,"Temperate","Standard"],"hoodle|needoll":["lovander",1,83,"Temperate","Standard"],"hoodle|surfent":["dinossom",1,83,"Temperate","Standard"],"hoodle|ribbuny-botan":["loupmoon",1,83,"Temperate","Standard"],"hoodle|kelpsea-ignis":["grintale",1,84,"Temperate","Standard"],"hoodle|muffly":["grintale",1,84,"Temperate","Standard"],"hoodle|pengullet-lux":["munchill",1,84,"Temperate","Standard"],"hangyu-cryst|hoodle":["gorirat",1,84,"Temperate","Standard"],"hoodle|killamari-primo":["sweepa",1,85,"Temperate","Standard"],"hoodle|nitewing":["sweepa",1,85,"Temperate","Standard"],"hoodle|jellroy":["sweepa",1,86,"Temperate","Standard"],"herbil|hoodle":["dazemu",1,87,"Temperate","Standard"],"hoodle|leezpunk-ignis":["dazemu",1,87,"Temperate","Standard"],"hoodle|jelliette":["dazemu",1,87,"Temperate","Standard"],"hoodle|leezpunk":["kingpaca",1,87,"Temperate","Standard"],"hoodle|melpaca":["finsider-ignis",1,88,"Temperate","Standard"],"hoodle|tocotoco":["wispaw",1,88,"Temperate","Standard"],"hoodle|mau-cryst":["robinquill",1,89,"Temperate","Standard"],"hoodle|killamari":["univolt",1,89,"Temperate","Standard"],"hangyu|hoodle":["univolt",1,89,"Temperate","Standard"],"hoodle|mozzarina":["elphidran",1,90,"Temperate","Standard"],"hoodle|kelpsea":["dumud",1,90,"Temperate","Standard"],"hoodle|woolipop":["dumud",1,90,"Temperate","Standard"],"hoodle|tanzee-ignis":["fuack-ignis",1,90,"Temperate","Standard"],"hoodle|swee":["fuack-ignis",1,91,"Temperate","Standard"],"hoodle|jolthog-cryst":["kikit",1,91,"Temperate","Standard"],"hoodle|ribbuny":["kikit",1,91,"Temperate","Standard"],"hoodle|rooby":["arsox",1,91,"Temperate","Standard"],"hoodle|rushoar":["arsox",1,91,"Temperate","Standard"],"hoodle|tanzee":["chillet",1,92,"Temperate","Standard"],"hoodle|nox":["tombat",1,92,"Temperate","Standard"],"hoodle|pupperai":["beegarde",1,92,"Temperate","Standard"],"hoocrates|hoodle":["beegarde",1,92,"Temperate","Standard"],"hoodle|pengullet":["puffolt",1,93,"Temperate","Standard"],"hoodle|sparkit":["snugloo",1,94,"Temperate","Standard"],"hoodle|lifmunk":["snugloo",1,94,"Temperate","Standard"],"hoodle|jolthog":["dazzi",1,94,"Temperate","Standard"],"hoodle|mau":["dazzi",1,94,"Temperate","Standard"],"hoodle|lamball":["turtacle",1,94,"Temperate","Standard"],"hoodle|vixy":["turtacle",1,95,"Temperate","Standard"],"hoodle|teafant":["needoll",1,95,"Temperate","Standard"],"hoodle|illuminant-bat":["gobfin-ignis",1,95,"Temperate","Standard"],"hoodle|illuminant-slime":["gobfin-ignis",1,95,"Temperate","Standard"],"hoodle|purple-slime":["gobfin-ignis",1,95,"Temperate","Standard"],"hoodle|rainbow-slime":["gobfin-ignis",1,95,"Temperate","Standard"],"hoodle|red-slime":["gobfin-ignis",1,95,"Temperate","Standard"],"hangyu-cryst|snock":["gorirat",1,85,"Temperate","Standard"],"herbil|snock":["dazemu",1,87,"Temperate","Standard"],"hangyu|snock":["elphidran",1,90,"Temperate","Standard"],"hoocrates|snock":["puffolt",1,93,"Temperate","Standard"],"hangyu-cryst|katress-ignis":["sweepa",1,85,"Temperate","Standard"],"herbil|katress-ignis":["dazemu",1,87,"Temperate","Standard"],"hangyu|katress-ignis":["dumud",1,90,"Temperate","Standard"],"hoocrates|katress-ignis":["cawgnito",1,93,"Temperate","Standard"],"hangyu-cryst|sibelyx":["sweepa",1,85,"Temperate","Standard"],"herbil|sibelyx":["kingpaca",1,87,"Temperate","Standard"],"hangyu|sibelyx":["dumud",1,90,"Temperate","Standard"],"hoocrates|sibelyx":["cawgnito",1,93,"Temperate","Standard"],"hangyu-cryst|xenovader":["sweepa",1,85,"Temperate","Standard"],"herbil|xenovader":["kingpaca",1,88,"Temperate","Standard"],"hangyu|xenovader":["fuack-ignis",1,90,"Temperate","Standard"],"hoocrates|xenovader":["celaray-lux",1,93,"Temperate","Standard"],"hangyu-cryst|surfent-terra":["sweepa",1,86,"Temperate","Standard"],"herbil|surfent-terra":["yakumo",1,88,"Temperate","Standard"],"hangyu|surfent-terra":["kikit",1,91,"Temperate","Standard"],"hoocrates|surfent-terra":["snugloo",1,94,"Temperate","Standard"],"hangyu-cryst|penking-lux":["sweepa",1,86,"Temperate","Standard"],"herbil|penking-lux":["finsider-ignis",1,88,"Temperate","Standard"],"hangyu|penking-lux":["kikit",1,91,"Temperate","Standard"],"hoocrates|penking-lux":["snugloo",1,94,"Temperate","Standard"],"hangyu-cryst|pyrin-noct":["dazemu",1,86,"Temperate","Standard"],"herbil|pyrin-noct":["wispaw",1,88,"Temperate","Standard"],"hangyu|pyrin-noct":["arsox",1,91,"Temperate","Standard"],"hoocrates|pyrin-noct":["dazzi",1,94,"Temperate","Standard"],"hangyu-cryst|valentail":["dazemu",1,87,"Temperate","Standard"],"herbil|valentail":["robinquill",1,89,"Temperate","Standard"],"hangyu|valentail":["tombat",1,92,"Temperate","Standard"],"hoocrates|valentail":["needoll",1,95,"Temperate","Standard"],"hangyu-cryst|rayhound":["dazemu",1,87,"Temperate","Standard"],"herbil|rayhound":["univolt",1,89,"Temperate","Standard"],"hangyu|rayhound":["beegarde",1,92,"Temperate","Standard"],"hoocrates|rayhound":["gobfin-ignis",1,95,"Temperate","Standard"],"hangyu-cryst|reindrix":["kingpaca",1,87,"Temperate","Standard"],"herbil|reindrix":["elphidran",1,90,"Temperate","Standard"],"hangyu|reindrix":["beegarde",1,92,"Temperate","Standard"],"hoocrates|reindrix":["gobfin-ignis",1,95,"Temperate","Standard"],"hangyu-cryst|pyrin":["finsider-ignis",1,88,"Temperate","Standard"],"herbil|pyrin":["fuack-ignis",1,91,"Temperate","Standard"],"hangyu|pyrin":["celaray-lux",1,93,"Temperate","Standard"],"hoocrates|pyrin":["ribbuny-botan",1,96,"Temperate","Standard"],"hangyu-cryst|lullu":["wispaw",1,88,"Temperate","Standard"],"herbil|lullu":["kikit",1,91,"Temperate","Standard"],"hangyu|lullu":["celaray-lux",1,93,"Temperate","Standard"],"hoocrates|lullu":["ribbuny-botan",1,96,"Temperate","Standard"],"hangyu-cryst|lunaris":["robinquill",1,89,"Temperate","Standard"],"herbil|lunaris":["arsox",1,91,"Temperate","Standard"],"hangyu|lunaris":["snugloo",1,94,"Temperate","Standard"],"hoocrates|lunaris":["kelpsea-ignis",1,97,"Temperate","Standard"],"hangyu-cryst|woolipop-terra":["univolt",1,89,"Temperate","Standard"],"herbil|woolipop-terra":["chillet",1,91,"Temperate","Standard"],"hangyu|woolipop-terra":["dazzi",1,94,"Temperate","Standard"],"hoocrates|woolipop-terra":["muffly",1,97,"Temperate","Standard"],"hangyu-cryst|katress":["univolt",1,89,"Temperate","Standard"],"herbil|katress":["chillet",1,92,"Temperate","Standard"],"hangyu|katress":["turtacle",1,94,"Temperate","Standard"],"hoocrates|katress":["pengullet-lux",1,97,"Temperate","Standard"],"hangyu-cryst|robinquill-terra":["elphidran",1,90,"Temperate","Standard"],"herbil|robinquill-terra":["tombat",1,92,"Temperate","Standard"],"hangyu|robinquill-terra":["turtacle",1,95,"Temperate","Standard"],"hoocrates|robinquill-terra":["pengullet-lux",1,98,"Temperate","Standard"],"hangyu-cryst|mossanda":["elphidran",1,90,"Temperate","Standard"],"herbil|mossanda":["tombat",1,92,"Temperate","Standard"],"hangyu|mossanda":["needoll",1,95,"Temperate","Standard"],"hoocrates|mossanda":["foxparks-cryst",1,98,"Temperate","Standard"],"hangyu-cryst|penking":["dumud",1,90,"Temperate","Standard"],"herbil|penking":["beegarde",1,92,"Temperate","Standard"],"hangyu|penking":["needoll",1,95,"Temperate","Standard"],"hoocrates|penking":["foxparks-cryst",1,98,"Temperate","Standard"],"hangyu-cryst|wixen":["dumud",1,90,"Temperate","Standard"],"herbil|wixen":["beegarde",1,92,"Temperate","Standard"],"hangyu|wixen":["gobfin-ignis",1,95,"Temperate","Standard"],"hoocrates|wixen":["hangyu-cryst",1,98,"Temperate","Standard"],"hangyu-cryst|lovander":["fuack-ignis",1,90,"Temperate","Standard"],"herbil|lovander":["puffolt",1,93,"Temperate","Standard"],"hangyu|lovander":["gobfin-ignis",1,95,"Temperate","Standard"],"hoocrates|lovander":["hangyu-cryst",1,98,"Temperate","Standard"],"hangyu-cryst|loupmoon":["kikit",1,91,"Temperate","Standard"],"herbil|loupmoon":["cawgnito",1,93,"Temperate","Standard"],"hangyu|loupmoon":["surfent",1,96,"Temperate","Standard"],"hoocrates|loupmoon":["amione",1,99,"Temperate","Standard"],"hangyu-cryst|munchill":["arsox",1,91,"Temperate","Standard"],"herbil|munchill":["celaray-lux",1,93,"Temperate","Standard"],"hangyu|munchill":["finsider",1,96,"Temperate","Standard"],"hoocrates|munchill":["gloopie",1,99,"Temperate","Standard"],"hangyu-cryst|sweepa":["chillet",1,91,"Temperate","Standard"],"herbil|sweepa":["snugloo",1,94,"Temperate","Standard"],"hangyu|sweepa":["ribbuny-botan",1,96,"Temperate","Standard"],"hoocrates|sweepa":["killamari-primo",1,99,"Temperate","Standard"],"hangyu-cryst|kingpaca":["puffolt",1,93,"Temperate","Standard"],"herbil|kingpaca":["needoll",1,95,"Temperate","Standard"],"hangyu|kingpaca":["foxparks-cryst",1,98,"Temperate","Standard"],"hoocrates|kingpaca":["eikthyrdeer-terra",1,101,"Temperate","Standard"],"hangyu-cryst|yakumo":["cawgnito",1,93,"Temperate","Standard"],"herbil|yakumo":["gobfin-ignis",1,95,"Temperate","Standard"],"hangyu|yakumo":["foxparks-cryst",1,98,"Temperate","Standard"],"hoocrates|yakumo":["eikthyrdeer-terra",1,101,"Temperate","Standard"],"hangyu-cryst|wispaw":["celaray-lux",1,93,"Temperate","Standard"],"herbil|wispaw":["surfent",1,96,"Temperate","Standard"],"hangyu|wispaw":["hangyu-cryst",1,98,"Temperate","Standard"],"hoocrates|wispaw":["jellroy",1,101,"Temperate","Standard"],"hangyu-cryst|robinquill":["celaray-lux",1,93,"Temperate","Standard"],"herbil|robinquill":["surfent",1,96,"Temperate","Standard"],"hangyu|robinquill":["amione",1,98,"Temperate","Standard"],"hoocrates|robinquill":["croajiro",1,101,"Temperate","Standard"],"hangyu-cryst|univolt":["snugloo",1,94,"Temperate","Standard"],"herbil|univolt":["finsider",1,96,"Temperate","Standard"],"hangyu|univolt":["amione",1,99,"Temperate","Standard"],"hoocrates|univolt":["croajiro",1,102,"Temperate","Standard"],"hangyu-cryst|kikit":["turtacle",1,94,"Temperate","Standard"],"herbil|kikit":["kelpsea-ignis",1,97,"Temperate","Standard"],"hangyu|kikit":["killamari-primo",1,99,"Temperate","Standard"],"hoocrates|kikit":["cinnamoth",1,102,"Temperate","Standard"],"hangyu-cryst|tombat":["needoll",1,95,"Temperate","Standard"],"herbil|tombat":["muffly",1,97,"Temperate","Standard"],"hangyu|tombat":["nitewing",1,100,"Temperate","Standard"],"hoocrates|tombat":["leezpunk-ignis",1,103,"Temperate","Standard"],"hangyu-cryst|puffolt":["gobfin-ignis",1,95,"Temperate","Standard"],"herbil|puffolt":["pengullet-lux",1,98,"Temperate","Standard"],"hangyu|puffolt":["galeclaw",1,100,"Temperate","Standard"],"hoocrates|puffolt":["jelliette",1,103,"Temperate","Standard"],"hangyu-cryst|snugloo":["finsider",1,96,"Temperate","Standard"],"herbil|snugloo":["hangyu-cryst",1,98,"Temperate","Standard"],"hangyu|snugloo":["eikthyrdeer-terra",1,101,"Temperate","Standard"],"hoocrates|snugloo":["flopie",1,104,"Temperate","Standard"],"hangyu-cryst|turtacle":["ribbuny-botan",1,96,"Temperate","Standard"],"herbil|turtacle":["amione",1,98,"Temperate","Standard"],"hangyu|turtacle":["jellroy",1,101,"Temperate","Standard"],"hoocrates|turtacle":["leezpunk",1,104,"Temperate","Standard"],"hangyu-cryst|needoll":["ribbuny-botan",1,96,"Temperate","Standard"],"herbil|needoll":["amione",1,99,"Temperate","Standard"],"hangyu|needoll":["croajiro",1,101,"Temperate","Standard"],"hoocrates|needoll":["direhowl",1,104,"Temperate","Standard"],"hangyu-cryst|surfent":["kelpsea-ignis",1,97,"Temperate","Standard"],"herbil|surfent":["gloopie",1,99,"Temperate","Standard"],"hangyu|surfent":["caprity",1,102,"Temperate","Standard"],"hoocrates|surfent":["bristla",1,105,"Temperate","Standard"],"hangyu-cryst|ribbuny-botan":["muffly",1,97,"Temperate","Standard"],"herbil|ribbuny-botan":["killamari-primo",1,99,"Temperate","Standard"],"hangyu|ribbuny-botan":["cinnamoth",1,102,"Temperate","Standard"],"hoocrates|ribbuny-botan":["flambelle",1,105,"Temperate","Standard"],"hangyu-cryst|kelpsea-ignis":["pengullet-lux",1,97,"Temperate","Standard"],"herbil|kelpsea-ignis":["gobfin",1,100,"Temperate","Standard"],"hangyu|kelpsea-ignis":["cinnamoth",1,102,"Temperate","Standard"],"hoocrates|kelpsea-ignis":["flambelle",1,105,"Temperate","Standard"],"hangyu-cryst|muffly":["pengullet-lux",1,98,"Temperate","Standard"],"herbil|muffly":["gobfin",1,100,"Temperate","Standard"],"hangyu|muffly":["herbil",1,103,"Temperate","Standard"],"hoocrates|muffly":["eikthyrdeer",1,106,"Temperate","Standard"],"hangyu-cryst|pengullet-lux":["foxparks-cryst",1,98,"Temperate","Standard"],"herbil|pengullet-lux":["nitewing",1,100,"Temperate","Standard"],"hangyu|pengullet-lux":["herbil",1,103,"Temperate","Standard"],"hoocrates|pengullet-lux":["eikthyrdeer",1,106,"Temperate","Standard"],"hangyu-cryst|hangyu-cryst":["foxparks-cryst",1,98,"Temperate","Standard"],"hangyu-cryst|killamari-primo":["amione",1,99,"Temperate","Standard"],"hangyu-cryst|nitewing":["gloopie",1,99,"Temperate","Standard"],"hangyu-cryst|jellroy":["gobfin",1,100,"Temperate","Standard"],"hangyu-cryst|herbil":["galeclaw",1,100,"Temperate","Standard"],"hangyu-cryst|leezpunk-ignis":["galeclaw",1,101,"Temperate","Standard"],"hangyu-cryst|jelliette":["eikthyrdeer-terra",1,101,"Temperate","Standard"],"hangyu-cryst|leezpunk":["jellroy",1,101,"Temperate","Standard"],"hangyu-cryst|melpaca":["caprity",1,102,"Temperate","Standard"],"hangyu-cryst|tocotoco":["cinnamoth",1,102,"Temperate","Standard"],"hangyu-cryst|mau-cryst":["herbil",1,103,"Temperate","Standard"],"hangyu-cryst|killamari":["leezpunk-ignis",1,103,"Temperate","Standard"],"hangyu|hangyu-cryst":["leezpunk-ignis",1,103,"Temperate","Standard"],"hangyu-cryst|mozzarina":["jelliette",1,103,"Temperate","Standard"],"hangyu-cryst|kelpsea":["flopie",1,104,"Temperate","Standard"],"hangyu-cryst|woolipop":["flopie",1,104,"Temperate","Standard"],"hangyu-cryst|tanzee-ignis":["leezpunk",1,104,"Temperate","Standard"],"hangyu-cryst|swee":["leezpunk",1,104,"Temperate","Standard"],"hangyu-cryst|jolthog-cryst":["direhowl",1,104,"Temperate","Standard"],"hangyu-cryst|ribbuny":["direhowl",1,105,"Temperate","Standard"],"hangyu-cryst|rooby":["bristla",1,105,"Temperate","Standard"],"hangyu-cryst|rushoar":["bristla",1,105,"Temperate","Standard"],"hangyu-cryst|tanzee":["flambelle",1,105,"Temperate","Standard"],"hangyu-cryst|nox":["eikthyrdeer",1,106,"Temperate","Standard"],"hangyu-cryst|pupperai":["melpaca",1,106,"Temperate","Standard"],"hangyu-cryst|hoocrates":["melpaca",1,106,"Temperate","Standard"],"hangyu-cryst|pengullet":["tocotoco",1,106,"Temperate","Standard"],"hangyu-cryst|sparkit":["cattiva",1,107,"Temperate","Standard"],"hangyu-cryst|lifmunk":["cattiva",1,108,"Temperate","Standard"],"hangyu-cryst|jolthog":["killamari",1,108,"Temperate","Standard"],"hangyu-cryst|mau":["killamari",1,108,"Temperate","Standard"],"hangyu-cryst|lamball":["hangyu",1,108,"Temperate","Standard"],"hangyu-cryst|vixy":["hangyu",1,108,"Temperate","Standard"],"hangyu-cryst|teafant":["fuddler",1,108,"Temperate","Standard"],"hangyu-cryst|illuminant-bat":["mozzarina",1,109,"Temperate","Standard"],"hangyu-cryst|illuminant-slime":["mozzarina",1,109,"Temperate","Standard"],"hangyu-cryst|purple-slime":["mozzarina",1,109,"Temperate","Standard"],"hangyu-cryst|rainbow-slime":["mozzarina",1,109,"Temperate","Standard"],"hangyu-cryst|red-slime":["mozzarina",1,109,"Temperate","Standard"],"herbil|killamari-primo":["eikthyrdeer-terra",1,101,"Temperate","Standard"],"hangyu|killamari-primo":["flopie",1,104,"Temperate","Standard"],"hoocrates|killamari-primo":["celaray",1,107,"Temperate","Standard"],"herbil|nitewing":["jellroy",1,101,"Temperate","Standard"],"hangyu|nitewing":["leezpunk",1,104,"Temperate","Standard"],"hoocrates|nitewing":["mau-cryst",1,107,"Temperate","Standard"],"herbil|jellroy":["caprity",1,102,"Temperate","Standard"],"hangyu|jellroy":["direhowl",1,105,"Temperate","Standard"],"hoocrates|jellroy":["cattiva",1,108,"Temperate","Standard"],"herbil|herbil":["cinnamoth",1,103,"Temperate","Standard"],"herbil|leezpunk-ignis":["cinnamoth",1,103,"Temperate","Standard"],"herbil|jelliette":["leezpunk-ignis",1,103,"Temperate","Standard"],"herbil|leezpunk":["jelliette",1,103,"Temperate","Standard"],"herbil|melpaca":["leezpunk",1,104,"Temperate","Standard"],"herbil|tocotoco":["direhowl",1,104,"Temperate","Standard"],"herbil|mau-cryst":["bristla",1,105,"Temperate","Standard"],"herbil|killamari":["flambelle",1,105,"Temperate","Standard"],"hangyu|herbil":["flambelle",1,105,"Temperate","Standard"],"herbil|mozzarina":["eikthyrdeer",1,106,"Temperate","Standard"],"herbil|kelpsea":["melpaca",1,106,"Temperate","Standard"],"herbil|woolipop":["melpaca",1,106,"Temperate","Standard"],"herbil|tanzee-ignis":["tocotoco",1,106,"Temperate","Standard"],"herbil|swee":["tocotoco",1,106,"Temperate","Standard"],"herbil|jolthog-cryst":["celaray",1,107,"Temperate","Standard"],"herbil|ribbuny":["celaray",1,107,"Temperate","Standard"],"herbil|rooby":["mau-cryst",1,107,"Temperate","Standard"],"herbil|rushoar":["mau-cryst",1,107,"Temperate","Standard"],"herbil|tanzee":["cattiva",1,108,"Temperate","Standard"],"herbil|nox":["killamari",1,108,"Temperate","Standard"],"herbil|pupperai":["hangyu",1,108,"Temperate","Standard"],"herbil|hoocrates":["hangyu",1,108,"Temperate","Standard"],"herbil|pengullet":["fuddler",1,109,"Temperate","Standard"],"herbil|sparkit":["woolipop",1,110,"Temperate","Standard"],"herbil|lifmunk":["woolipop",1,110,"Temperate","Standard"],"herbil|jolthog":["tanzee-ignis",1,110,"Temperate","Standard"],"herbil|mau":["tanzee-ignis",1,110,"Temperate","Standard"],"herbil|lamball":["swee",1,110,"Temperate","Standard"],"herbil|vixy":["swee",1,111,"Temperate","Standard"],"herbil|teafant":["jolthog-cryst",1,111,"Temperate","Standard"],"herbil|illuminant-bat":["ribbuny",1,111,"Temperate","Standard"],"herbil|illuminant-slime":["ribbuny",1,111,"Temperate","Standard"],"herbil|purple-slime":["ribbuny",1,111,"Temperate","Standard"],"herbil|rainbow-slime":["ribbuny",1,111,"Temperate","Standard"],"herbil|red-slime":["ribbuny",1,111,"Temperate","Standard"],"hangyu|leezpunk-ignis":["eikthyrdeer",1,106,"Temperate","Standard"],"hoocrates|leezpunk-ignis":["fuddler",1,108,"Temperate","Standard"],"hangyu|jelliette":["eikthyrdeer",1,106,"Temperate","Standard"],"hoocrates|jelliette":["fuddler",1,109,"Temperate","Standard"],"hangyu|leezpunk":["melpaca",1,106,"Temperate","Standard"],"hoocrates|leezpunk":["mozzarina",1,109,"Temperate","Standard"],"hangyu|melpaca":["mau-cryst",1,107,"Temperate","Standard"],"hoocrates|melpaca":["tanzee-ignis",1,110,"Temperate","Standard"],"hangyu|tocotoco":["mau-cryst",1,107,"Temperate","Standard"],"hoocrates|tocotoco":["tanzee-ignis",1,110,"Temperate","Standard"],"hangyu|mau-cryst":["cattiva",1,108,"Temperate","Standard"],"hoocrates|mau-cryst":["swee",1,111,"Temperate","Standard"],"hangyu|killamari":["cattiva",1,108,"Temperate","Standard"],"hoocrates|killamari":["jolthog-cryst",1,111,"Temperate","Standard"],"hangyu|hangyu":["killamari",1,108,"Temperate","Standard"],"hangyu|mozzarina":["fuddler",1,108,"Temperate","Standard"],"hangyu|kelpsea":["fuddler",1,109,"Temperate","Standard"],"hangyu|woolipop":["mozzarina",1,109,"Temperate","Standard"],"hangyu|tanzee-ignis":["mozzarina",1,109,"Temperate","Standard"],"hangyu|swee":["kelpsea",1,109,"Temperate","Standard"],"hangyu|jolthog-cryst":["kelpsea",1,109,"Temperate","Standard"],"hangyu|ribbuny":["woolipop",1,110,"Temperate","Standard"],"hangyu|rooby":["woolipop",1,110,"Temperate","Standard"],"hangyu|rushoar":["tanzee-ignis",1,110,"Temperate","Standard"],"hangyu|tanzee":["swee",1,110,"Temperate","Standard"],"hangyu|nox":["jolthog-cryst",1,111,"Temperate","Standard"],"hangyu|pupperai":["jolthog-cryst",1,111,"Temperate","Standard"],"hangyu|hoocrates":["ribbuny",1,111,"Temperate","Standard"],"hangyu|pengullet":["rooby",1,111,"Temperate","Standard"],"hangyu|sparkit":["cremis",1,112,"Temperate","Standard"],"hangyu|lifmunk":["tanzee",1,113,"Temperate","Standard"],"hangyu|jolthog":["tanzee",1,113,"Temperate","Standard"],"hangyu|mau":["daedream",1,113,"Temperate","Standard"],"hangyu|lamball":["daedream",1,113,"Temperate","Standard"],"hangyu|vixy":["nox",1,113,"Temperate","Standard"],"hangyu|teafant":["nox",1,114,"Temperate","Standard"],"hangyu|illuminant-bat":["hoocrates",1,114,"Temperate","Standard"],"hangyu|illuminant-slime":["hoocrates",1,114,"Temperate","Standard"],"hangyu|purple-slime":["hoocrates",1,114,"Temperate","Standard"],"hangyu|rainbow-slime":["hoocrates",1,114,"Temperate","Standard"],"hangyu|red-slime":["hoocrates",1,114,"Temperate","Standard"],"hoocrates|mozzarina":["rooby",1,111,"Temperate","Standard"],"hoocrates|kelpsea":["rooby",1,112,"Temperate","Standard"],"hoocrates|woolipop":["rushoar",1,112,"Temperate","Standard"],"hoocrates|tanzee-ignis":["rushoar",1,112,"Temperate","Standard"],"hoocrates|swee":["cremis",1,112,"Temperate","Standard"],"hoocrates|jolthog-cryst":["cremis",1,112,"Temperate","Standard"],"hoocrates|ribbuny":["tanzee",1,113,"Temperate","Standard"],"hoocrates|rooby":["tanzee",1,113,"Temperate","Standard"],"hoocrates|rushoar":["daedream",1,113,"Temperate","Standard"],"hoocrates|tanzee":["nox",1,113,"Temperate","Standard"],"hoocrates|nox":["pupperai",1,114,"Temperate","Standard"],"hoocrates|pupperai":["nox",1,114,"Temperate","Standard"],"hoocrates|hoocrates":["pupperai",1,114,"Temperate","Standard"],"hoocrates|pengullet":["gumoss",1,114,"Temperate","Standard"],"hoocrates|sparkit":["clovee",1,115,"Temperate","Standard"],"hoocrates|lifmunk":["fuack",1,116,"Temperate","Standard"],"hoocrates|jolthog":["fuack",1,116,"Temperate","Standard"],"hoocrates|mau":["foxparks",1,116,"Temperate","Standard"],"hoocrates|lamball":["foxparks",1,116,"Temperate","Standard"],"hoocrates|vixy":["foxparks",1,116,"Temperate","Standard"],"hoocrates|teafant":["sparkit",1,116,"Temperate","Standard"],"hoocrates|illuminant-bat":["lifmunk",1,117,"Temperate","Standard"],"hoocrates|illuminant-slime":["lifmunk",1,117,"Temperate","Standard"],"hoocrates|purple-slime":["lifmunk",1,117,"Temperate","Standard"],"hoocrates|rainbow-slime":["lifmunk",1,117,"Temperate","Standard"],"hoocrates|red-slime":["lifmunk",1,117,"Temperate","Standard"]}